rtl/can_arbitration.sv
//-----------------------------------------------------------------------------
// can_arbitration
// Comparador bitwise do campo de Arbitration. NÃO drive o barramento.
// Em cada sample_tick (com arb_en): se transmitimos recessivo (1) e o bus
// está dominante (0), perdemos a arbitragem. Conta o bit em que ocorreu.
//-----------------------------------------------------------------------------
module can_arbitration (
    input  logic        clk,
    input  logic        rst_n,

    input  logic        sample_tick,   // 1 pulso por bit (do BTU/FSM)
    input  logic        arb_en,        // 1 durante o campo de Arbitration
    input  logic        tx_bit,        // bit que transmitimos (do FSM)
    input  logic        rx_bit,        // bit amostrado no bus (do BSP)

    output logic        arb_lost,      // 1 = perdemos a arbitragem
    output logic        arb_active,    // 1 = ainda competindo
    output logic [5:0]  arb_lost_bit   // índice do bit em que perdemos
);

    logic       lost_r;
    logic [5:0] bit_cnt;
    logic [5:0] lost_bit_r;

    always_ff @(posedge clk or negedge rst_n) begin
        if (!rst_n) begin
            lost_r     <= 1'b0;
            bit_cnt    <= 6'd0;
            lost_bit_r <= 6'd0;
        end else if (!arb_en) begin
            // fora do campo de arbitragem: reinicia
            lost_r     <= 1'b0;
            bit_cnt    <= 6'd0;
            lost_bit_r <= 6'd0;
        end else if (sample_tick && !lost_r) begin
            if (tx_bit && !rx_bit) begin   // tx recessivo (1), bus dominante (0)
                lost_r     <= 1'b1;
                lost_bit_r <= bit_cnt;
            end
            bit_cnt <= bit_cnt + 6'd1;
        end
    end

    assign arb_lost     = lost_r;
    assign arb_active   = arb_en && !lost_r;
    assign arb_lost_bit = lost_bit_r;

endmodule

uvm/testbench/tb_can_arbitration.sv
//-----------------------------------------------------------------------------
// tb_can_arbitration — Testbench SIMPLES (smoke test, self-checking, nao-UVM)
// do can_arbitration.
//
// Cobre:
//   - Pós-reset: arb_lost=0, arb_active=0 (arb_en=0).
//   - Sem perda quando tx_bit sempre dominante (== rx_bit).
//   - Perda quando tx recessivo (1) e bus dominante (0) -> arb_lost=1 em
//     arb_lost_bit correto.
//   - arb_active cai quando lost.
//   - Reinicio quando arb_en volta a 0.
//
// Rodar (Xcelium):
//   xrun -sv -access +rwc -timescale 1ns/1ps -f script/simlist_can.f \
//        uvm/testbench/tb_can_arbitration.sv
// Icarus:
//   iverilog -g2012 -t null -f script/simlist_can.f uvm/testbench/tb_can_arbitration.sv
//-----------------------------------------------------------------------------
`timescale 1ns/1ps

module tb_can_arbitration;

    logic        clk = 1'b0;
    logic        rst_n;
    logic        sample_tick, arb_en, tx_bit, rx_bit;
    logic        arb_lost, arb_active;
    logic [5:0]  arb_lost_bit;

    can_arbitration DUT (
        .clk(clk), .rst_n(rst_n),
        .sample_tick(sample_tick), .arb_en(arb_en),
        .tx_bit(tx_bit), .rx_bit(rx_bit),
        .arb_lost(arb_lost), .arb_active(arb_active), .arb_lost_bit(arb_lost_bit)
    );

    always #10 clk = ~clk;

    integer errors;

    task chk(input bit cond, input string msg);
        begin
            if (!cond) begin errors = errors + 1; $display("[TB] FAIL: %s", msg); end
            else         $display("[TB] OK:   %s", msg);
        end
    endtask

    // strobe: pulsa sample_tick por 1 ciclo
    task sample;
        begin
            @(negedge clk); sample_tick = 1'b1;
            @(negedge clk); sample_tick = 1'b0;
        end
    endtask

    initial begin
        $timeformat(-9, 3, " ns", 12);
        errors = 0;
        sample_tick = 1'b0; arb_en = 1'b0; tx_bit = 1'b0; rx_bit = 1'b0;

        $dumpfile("tb_can_arbitration.vcd");
        $dumpvars(0, tb_can_arbitration);

        rst_n = 1'b0;
        repeat (3) @(posedge clk);
        rst_n = 1'b1;
        @(posedge clk);

        $display("==========================================================");
        $display("[TB] tb_can_arbitration — smoke test");
        $display("==========================================================");

        // 1) Pós-reset com arb_en=0
        chk(arb_lost === 1'b0,       "arb_lost=0 pos-reset");
        chk(arb_active === 1'b0,     "arb_active=0 pos-reset (arb_en=0)");
        chk(arb_lost_bit === 6'd0,   "arb_lost_bit=0 pos-reset");

        // 2) arb_en=1, todo dominante e bus dominante -> não perde em 12 bits
        arb_en = 1'b1;
        tx_bit = 1'b0; rx_bit = 1'b0;
        for (int i = 0; i < 12; i++) begin
            sample;
            if (arb_lost !== 1'b0) begin
                errors = errors + 1;
                $display("[TB] FAIL: arb_lost=1 inesperado no bit %0d", i);
                i = 12;
            end
        end
        if (errors == 0)
            $display("[TB] OK:   12 bits dominantes -> sem perda");
        chk(arb_active === 1'b1,     "arb_active=1 enquanto competindo");

        // 3) Reinicia com arb_en=0 (checa no negedge p/ evitar race c/ always_ff)
        arb_en = 1'b0;
        @(negedge clk);
        chk(arb_lost === 1'b0,       "arb_lost reinicia quando arb_en=0");

        // 4) Perda: tx recessivo (1), bus dominante (0) no bit 5 (6º bit)
        arb_en = 1'b1;
        tx_bit = 1'b0; rx_bit = 1'b0;   // bits 0..4 dominantes (ganha)
        for (int i = 0; i < 5; i++) sample;
        chk(arb_lost === 1'b0,       "5 bits dominantes iniciais: sem perda");
        tx_bit = 1'b1; rx_bit = 1'b0;   // bit 5: perde
        sample;
        chk(arb_lost === 1'b1,       "bit 5 tx=1/rx=0 -> arb_lost=1");
        chk(arb_lost_bit === 6'd5,   "arb_lost_bit=5");
        chk(arb_active === 1'b0,     "arb_active=0 apos perda");
        // Continua competindo (perdeu) e o lost_bit não muda
        sample; sample;
        chk(arb_lost_bit === 6'd5,   "arb_lost_bit sticky (=5)");

        // 5) arb_en=0 reinicia lost_r (checa no negedge p/ evitar race)
        arb_en = 1'b0;
        @(negedge clk);
        chk(arb_lost === 1'b0,       "arb_lost reinicia quando arb_en desliga");

        $display("----------------------------------------------------------");
        if (errors == 0) $display("[TB] ===== SMOKE TEST PASS =====");
        else             $display("[TB] ===== SMOKE TEST FAIL (%0d erros) =====", errors);
        $display("----------------------------------------------------------");
        $finish;
    end

    initial begin
        #1ms;
        $display("[TB] TIMEOUT global (1 ms). Abortando.");
        $finish;
    end

endmodule

tb_can_arbitration.vcd
$date
	Tue Jul 07 22:07:18 2026
$end
$version
	Icarus Verilog
$end
$timescale
	1ps
$end
$scope module tb_can_arbitration $end
$var wire 6 ! arb_lost_bit [5:0] $end
$var wire 1 " arb_lost $end
$var wire 1 # arb_active $end
$var reg 1 $ arb_en $end
$var reg 1 % clk $end
$var reg 1 & rst_n $end
$var reg 1 ' rx_bit $end
$var reg 1 ( sample_tick $end
$var reg 1 ) tx_bit $end
$var integer 32 * errors [31:0] $end
$scope module DUT $end
$var wire 1 # arb_active $end
$var wire 1 $ arb_en $end
$var wire 1 " arb_lost $end
$var wire 6 + arb_lost_bit [5:0] $end
$var wire 1 % clk $end
$var wire 1 & rst_n $end
$var wire 1 ' rx_bit $end
$var wire 1 ( sample_tick $end
$var wire 1 ) tx_bit $end
$var reg 6 , bit_cnt [5:0] $end
$var reg 6 - lost_bit_r [5:0] $end
$var reg 1 . lost_r $end
$upscope $end
$scope begin $ivl_for_loop0 $end
$var integer 32 / i [31:0] $end
$upscope $end
$scope begin $ivl_for_loop1 $end
$var integer 32 0 i [31:0] $end
$upscope $end
$scope task chk $end
$var reg 1 1 cond $end
$upscope $end
$scope task sample $end
$upscope $end
$upscope $end
$enddefinitions $end
$comment Show the parameter values. $end
$dumpall
$end
#0
$dumpvars
01
b0 0
b0 /
0.
b0 -
b0 ,
b0 +
b0 *
0)
0(
0'
0&
0%
0$
0#
0"
b0 !
$end
#10000
1%
#20000
0%
#30000
1%
#40000
0%
#50000
1&
1%
#60000
0%
#70000
1#
1$
11
1%
#80000
1(
0%
#90000
b1 ,
1%
#100000
b1 /
0(
0%
#110000
1%
#120000
1(
0%
#130000
b10 ,
1%
#140000
b10 /
0(
0%
#150000
1%
#160000
1(
0%
#170000
b11 ,
1%
#180000
b11 /
0(
0%
#190000
1%
#200000
1(
0%
#210000
b100 ,
1%
#220000
b100 /
0(
0%
#230000
1%
#240000
1(
0%
#250000
b101 ,
1%
#260000
b101 /
0(
0%
#270000
1%
#280000
1(
0%
#290000
b110 ,
1%
#300000
b110 /
0(
0%
#310000
1%
#320000
1(
0%
#330000
b111 ,
1%
#340000
b111 /
0(
0%
#350000
1%
#360000
1(
0%
#370000
b1000 ,
1%
#380000
b1000 /
0(
0%
#390000
1%
#400000
1(
0%
#410000
b1001 ,
1%
#420000
b1001 /
0(
0%
#430000
1%
#440000
1(
0%
#450000
b1010 ,
1%
#460000
b1010 /
0(
0%
#470000
1%
#480000
1(
0%
#490000
b1011 ,
1%
#500000
b1011 /
0(
0%
#510000
1%
#520000
1(
0%
#530000
b1100 ,
1%
#540000
0#
0$
b1100 /
0(
0%
#550000
b0 ,
1%
#560000
1#
1$
0%
#570000
1%
#580000
1(
0%
#590000
b1 ,
1%
#600000
b1 0
0(
0%
#610000
1%
#620000
1(
0%
#630000
b10 ,
1%
#640000
b10 0
0(
0%
#650000
1%
#660000
1(
0%
#670000
b11 ,
1%
#680000
b11 0
0(
0%
#690000
1%
#700000
1(
0%
#710000
b100 ,
1%
#720000
b100 0
0(
0%
#730000
1%
#740000
1(
0%
#750000
b101 ,
1%
#760000
1)
b101 0
0(
0%
#770000
1%
#780000
1(
0%
#790000
0#
b110 ,
b101 !
b101 +
b101 -
1"
1.
1%
#800000
0(
0%
#810000
1%
#820000
1(
0%
#830000
1%
#840000
0(
0%
#850000
1%
#860000
1(
0%
#870000
1%
#880000
0$
0(
0%
#890000
b0 !
b0 +
b0 -
b0 ,
0"
0.
1%
