rtl/can_crc.sv
//-----------------------------------------------------------------------------
// can_crc
// CRC-15 bit-serial do CAN (polinômio 0x4599). Processa 1 bit por crc_shift.
// crc_clear zera o LFSR (início do frame). check_strobe compara rx_crc.
//-----------------------------------------------------------------------------
module can_crc (
    input  logic        clk,
    input  logic        rst_n,

    // cálculo (controlado pelo FSM)
    input  logic        crc_clear,    // zera o LFSR
    input  logic        crc_shift,    // strobe: inclui bit_in
    input  logic        bit_in,       // bit (destuffed) a incluir

    // resultado
    output logic [14:0] crc_out,

    // verificação (campo CRC, recepção)
    input  logic [14:0] rx_crc,       // CRC recebido do frame
    input  logic        check_strobe, // compara rx_crc com crc_out
    output logic        crc_match,    // 1 se rx_crc == crc_out (no strobe; sticky)
    output logic        crc_error     // 1 se rx_crc != crc_out (no strobe; sticky)
);

    localparam logic [14:0] POLY = 15'h4599;

    logic [14:0] crc_reg;

    always_ff @(posedge clk or negedge rst_n) begin
        if (!rst_n)              crc_reg <= 15'h0;
        else if (crc_clear)      crc_reg <= 15'h0;
        else if (crc_shift)      crc_reg <= (crc_reg >> 1) ^ ((crc_reg[0] ^ bit_in) ? POLY : 15'h0);
    end

    assign crc_out = crc_reg;

    always_ff @(posedge clk or negedge rst_n) begin
        if (!rst_n) begin
            crc_match <= 1'b0;
            crc_error <= 1'b0;
        end else if (check_strobe) begin
            crc_match <= (rx_crc == crc_reg);
            crc_error <= (rx_crc != crc_reg);
        end
        // caso contrário: mantém (sticky) até o próximo strobe
    end

endmodule

uvm/testbench/tb_can_crc.sv
//-----------------------------------------------------------------------------
// tb_can_crc — Testbench SIMPLES (smoke test, self-checking, nao-UVM) do
// can_crc (CRC-15 bit-serial, poly 0x4599, LFSR init=0).
//
// Cobre:
//   - LFSR contra MODELO DE REFERENCIA bitwise (function) em SV, sobre
//     varias sequencias (todas 0, todas 1, padrao 0x123, aleatorio-rep).
//   - crc_clear zera o LFSR.
//   - check_strobe: rx_crc==crc_out -> crc_match=1; != -> crc_error=1
//     (sinais sticky mantidos apos o strobe).
//
// Rodar (Xcelium):
//   xrun -sv -access +rwc -timescale 1ns/1ps -f script/simlist_can.f \
//        uvm/testbench/tb_can_crc.sv
// Icarus:
//   iverilog -g2012 -t null -f script/simlist_can.f uvm/testbench/tb_can_crc.sv
//-----------------------------------------------------------------------------
`timescale 1ns/1ps

module tb_can_crc;

    logic        clk = 1'b0;
    logic        rst_n;
    logic        crc_clear, crc_shift, bit_in;
    logic [14:0] crc_out;
    logic [14:0] rx_crc;
    logic        check_strobe;
    logic        crc_match, crc_error;

    can_crc DUT (
        .clk(clk), .rst_n(rst_n),
        .crc_clear(crc_clear), .crc_shift(crc_shift), .bit_in(bit_in),
        .crc_out(crc_out),
        .rx_crc(rx_crc), .check_strobe(check_strobe),
        .crc_match(crc_match), .crc_error(crc_error)
    );

    always #10 clk = ~clk;

    integer errors;

    // ---- Modelo de referência CRC-15 (poly 0x4599, init=0) ----
    function automatic bit [14:0] crc15_step(input bit [14:0] crc_in,
                                             input bit b);
        bit [14:0] crc = crc_in;
        if ((crc[0] ^ b) != 1'b0)
            crc = (crc >> 1) ^ 15'h4599;
        else
            crc = (crc >> 1);
        return crc;
    endfunction

    task chk(input bit cond, input string msg);
        begin
            if (!cond) begin errors = errors + 1; $display("[TB] FAIL: %s", msg); end
            else         $display("[TB] OK:   %s", msg);
        end
    endtask

    // Aplica uma sequência de bits e compara crc_out com o modelo.
    // seq_len = nº de bits; stream é empacotado MSB-first (bit mais
    // significativo é o primeiro transmitido).
    task run_stream(input int seq_len, input logic [63:0] stream);
        bit [14:0] crc_ref;     // modelo: init=0
        bit        mismatch;
        integer    i;
        bit        b;
        begin
            crc_ref  = 15'h0;
            mismatch = 1'b0;
            @(negedge clk);
            crc_clear = 1'b1;          // zera LFSR e modelo
            @(negedge clk);
            crc_clear = 1'b0;
            // processa seq_len bits MSB-first
            for (i = 0; i < seq_len; i = i + 1) begin
                b = stream[63 - (i % 64)];   // repete padrão se i>=64
                @(negedge clk);
                bit_in = b; crc_shift = 1'b1;
                crc_ref = crc15_step(crc_ref, b);
                @(negedge clk);
                crc_shift = 1'b0;
                // neste momento crc_out já reflete o passo (registrado)
                if (crc_out !== crc_ref && !mismatch) begin
                    mismatch = 1'b1;
                    errors = errors + 1;
                    $display("[TB] FAIL: CRC mismatch no bit %0d (DUT=%h REF=%h)",
                             i, crc_out, crc_ref);
                end
            end
            if (!mismatch)
                $display("[TB] OK:   CRC bateu em %0d bits (final=%h)",
                         seq_len, crc_out);
        end
    endtask

    initial begin
        $timeformat(-9, 3, " ns", 12);
        errors = 0;
        crc_clear = 1'b0; crc_shift = 1'b0; bit_in = 1'b0;
        rx_crc = 15'h0; check_strobe = 1'b0;

        $dumpfile("tb_can_crc.vcd");
        $dumpvars(0, tb_can_crc);

        rst_n = 1'b0;
        repeat (3) @(posedge clk);
        rst_n = 1'b1;
        @(posedge clk);

        $display("==========================================================");
        $display("[TB] tb_can_crc — smoke test");
        $display("==========================================================");

        // 1) Pós-reset: LFSR=0
        chk(crc_out === 15'h0, "crc_out=0 pos-reset");

        // 2) Sequências variadas contra modelo de referência
        run_stream(19, {64'h0});                 // ARB 11-bit + CTRL 6 + DATA0 2 (ex.)
        run_stream(64, 64'hFFFFFFFFFFFFFFFF);    // tudo recessivo
        run_stream(64, 64'h0123456789ABCDEF);
        run_stream(47, 64'hA5A5A5A5A5A5A5A5);    // SOF+ARB+CTRL+DATA(3 bytes) approx
        run_stream(16, 64'h00000000000000FF);

        // 3) crc_clear zera no meio de uma corrida
        @(negedge clk);
        crc_clear = 1'b1; bit_in = 1'b0; crc_shift = 1'b0;
        @(negedge clk);
        crc_clear = 1'b0;
        @(posedge clk);
        chk(crc_out === 15'h0, "crc_clear zera o LFSR");

        // 4) check_strobe -> crc_match / crc_error (sticky)
        // Prepara: após uma sequência conhecida, strobe com rx_crc igual e != .
        run_stream(16, 64'hFACEFACEFACEFACE);    // deixa crc_out num valor X
        @(negedge clk);
        rx_crc = crc_out;                         // deve casar
        check_strobe = 1'b1;
        @(negedge clk);
        check_strobe = 1'b0;
        @(posedge clk);
        chk(crc_match === 1'b1,  "check_strobe rx_crc==crc_out -> crc_match=1");
        chk(crc_error === 1'b0,  "...                            crc_error=0");

        @(negedge clk);
        rx_crc = ~crc_out;                        // não casa
        check_strobe = 1'b1;
        @(negedge clk);
        check_strobe = 1'b0;
        @(posedge clk);
        chk(crc_match === 1'b0,  "check_strobe rx_crc!=crc_out -> crc_match=0");
        chk(crc_error === 1'b1,  "...                            crc_error=1");

        // 5) Sticky: sem strobe, mantém
        @(negedge clk);
        @(posedge clk);
        chk(crc_error === 1'b1,  "crc_error sticky mantido sem novo strobe");

        $display("----------------------------------------------------------");
        if (errors == 0) $display("[TB] ===== SMOKE TEST PASS =====");
        else             $display("[TB] ===== SMOKE TEST FAIL (%0d erros) =====", errors);
        $display("----------------------------------------------------------");
        $finish;
    end

    initial begin
        #1ms;
        $display("[TB] TIMEOUT global (1 ms). Abortando.");
        $finish;
    end

endmodule

tb_can_crc.vcd
$date
	Tue Jul 07 22:07:18 2026
$end
$version
	Icarus Verilog
$end
$timescale
	1ps
$end
$scope module tb_can_crc $end
$var wire 15 ! crc_out [14:0] $end
$var wire 1 " crc_match $end
$var wire 1 # crc_error $end
$var reg 1 $ bit_in $end
$var reg 1 % check_strobe $end
$var reg 1 & clk $end
$var reg 1 ' crc_clear $end
$var reg 1 ( crc_shift $end
$var reg 1 ) rst_n $end
$var reg 15 * rx_crc [14:0] $end
$var integer 32 + errors [31:0] $end
$scope function crc15_step $end
$upscope $end
$scope module DUT $end
$var wire 1 $ bit_in $end
$var wire 1 % check_strobe $end
$var wire 1 & clk $end
$var wire 1 ' crc_clear $end
$var wire 15 , crc_out [14:0] $end
$var wire 1 ( crc_shift $end
$var wire 1 ) rst_n $end
$var wire 15 - rx_crc [14:0] $end
$var parameter 15 . POLY $end
$var reg 1 # crc_error $end
$var reg 1 " crc_match $end
$var reg 15 / crc_reg [14:0] $end
$upscope $end
$scope task chk $end
$var reg 1 0 cond $end
$upscope $end
$scope task run_stream $end
$var reg 64 1 stream [63:0] $end
$var reg 1 2 b $end
$var reg 15 3 crc_ref [14:0] $end
$var integer 32 4 i [31:0] $end
$var reg 1 5 mismatch $end
$var integer 32 6 seq_len [31:0] $end
$upscope $end
$upscope $end
$enddefinitions $end
$comment Show the parameter values. $end
$dumpall
b100010110011001 .
$end
#0
$dumpvars
b0 6
05
bx 4
b0 3
02
bx 1
00
b0 /
b0 -
b0 ,
b0 +
b0 *
0)
0(
0'
0&
0%
0$
0#
0"
b0 !
$end
#10000
1&
#20000
0&
#30000
1&
#40000
0&
#50000
1)
1&
#60000
0&
#70000
b0 1
b10011 6
10
1&
#80000
1'
0&
#90000
1&
#100000
b0 4
0'
0&
#110000
1&
#120000
1(
0&
#130000
1&
#140000
b1 4
0(
0&
#150000
1&
#160000
1(
0&
#170000
1&
#180000
b10 4
0(
0&
#190000
1&
#200000
1(
0&
#210000
1&
#220000
b11 4
0(
0&
#230000
1&
#240000
1(
0&
#250000
1&
#260000
b100 4
0(
0&
#270000
1&
#280000
1(
0&
#290000
1&
#300000
b101 4
0(
0&
#310000
1&
#320000
1(
0&
#330000
1&
#340000
b110 4
0(
0&
#350000
1&
#360000
1(
0&
#370000
1&
#380000
b111 4
0(
0&
#390000
1&
#400000
1(
0&
#410000
1&
#420000
b1000 4
0(
0&
#430000
1&
#440000
1(
0&
#450000
1&
#460000
b1001 4
0(
0&
#470000
1&
#480000
1(
0&
#490000
1&
#500000
b1010 4
0(
0&
#510000
1&
#520000
1(
0&
#530000
1&
#540000
b1011 4
0(
0&
#550000
1&
#560000
1(
0&
#570000
1&
#580000
b1100 4
0(
0&
#590000
1&
#600000
1(
0&
#610000
1&
#620000
b1101 4
0(
0&
#630000
1&
#640000
1(
0&
#650000
1&
#660000
b1110 4
0(
0&
#670000
1&
#680000
1(
0&
#690000
1&
#700000
b1111 4
0(
0&
#710000
1&
#720000
1(
0&
#730000
1&
#740000
b10000 4
0(
0&
#750000
1&
#760000
1(
0&
#770000
1&
#780000
b10001 4
0(
0&
#790000
1&
#800000
1(
0&
#810000
1&
#820000
b10010 4
0(
0&
#830000
1&
#840000
1(
0&
#850000
1&
#860000
b1111111111111111111111111111111111111111111111111111111111111111 1
b1000000 6
b10011 4
0(
0&
#870000
1&
#880000
1'
0&
#890000
1&
#900000
12
b0 4
0'
0&
#910000
1&
#920000
b100010110011001 3
1(
1$
0&
#930000
b100010110011001 !
b100010110011001 ,
b100010110011001 /
1&
#940000
b1 4
0(
0&
#950000
1&
#960000
b10001011001100 3
1(
0&
#970000
b10001011001100 !
b10001011001100 ,
b10001011001100 /
1&
#980000
b10 4
0(
0&
#990000
1&
#1000000
b101010011111111 3
1(
0&
#1010000
b101010011111111 !
b101010011111111 ,
b101010011111111 /
1&
#1020000
b11 4
0(
0&
#1030000
1&
#1040000
b10101001111111 3
1(
0&
#1050000
b10101001111111 !
b10101001111111 ,
b10101001111111 /
1&
#1060000
b100 4
0(
0&
#1070000
1&
#1080000
b1010100111111 3
1(
0&
#1090000
b1010100111111 !
b1010100111111 ,
b1010100111111 /
1&
#1100000
b101 4
0(
0&
#1110000
1&
#1120000
b101010011111 3
1(
0&
#1130000
b101010011111 !
b101010011111 ,
b101010011111 /
1&
#1140000
b110 4
0(
0&
#1150000
1&
#1160000
b10101001111 3
1(
0&
#1170000
b10101001111 !
b10101001111 ,
b10101001111 /
1&
#1180000
b111 4
0(
0&
#1190000
1&
#1200000
b1010100111 3
1(
0&
#1210000
b1010100111 !
b1010100111 ,
b1010100111 /
1&
#1220000
b1000 4
0(
0&
#1230000
1&
#1240000
b101010011 3
1(
0&
#1250000
b101010011 !
b101010011 ,
b101010011 /
1&
#1260000
b1001 4
0(
0&
#1270000
1&
#1280000
b10101001 3
1(
0&
#1290000
b10101001 !
b10101001 ,
b10101001 /
1&
#1300000
b1010 4
0(
0&
#1310000
1&
#1320000
b1010100 3
1(
0&
#1330000
b1010100 !
b1010100 ,
b1010100 /
1&
#1340000
b1011 4
0(
0&
#1350000
1&
#1360000
b100010110110011 3
1(
0&
#1370000
b100010110110011 !
b100010110110011 ,
b100010110110011 /
1&
#1380000
b1100 4
0(
0&
#1390000
1&
#1400000
b10001011011001 3
1(
0&
#1410000
b10001011011001 !
b10001011011001 ,
b10001011011001 /
1&
#1420000
b1101 4
0(
0&
#1430000
1&
#1440000
b1000101101100 3
1(
0&
#1450000
b1000101101100 !
b1000101101100 ,
b1000101101100 /
1&
#1460000
b1110 4
0(
0&
#1470000
1&
#1480000
b100110100101111 3
1(
0&
#1490000
b100110100101111 !
b100110100101111 ,
b100110100101111 /
1&
#1500000
b1111 4
0(
0&
#1510000
1&
#1520000
b10011010010111 3
1(
0&
#1530000
b10011010010111 !
b10011010010111 ,
b10011010010111 /
1&
#1540000
b10000 4
0(
0&
#1550000
1&
#1560000
b1001101001011 3
1(
0&
#1570000
b1001101001011 !
b1001101001011 ,
b1001101001011 /
1&
#1580000
b10001 4
0(
0&
#1590000
1&
#1600000
b100110100101 3
1(
0&
#1610000
b100110100101 !
b100110100101 ,
b100110100101 /
1&
#1620000
b10010 4
0(
0&
#1630000
1&
#1640000
b10011010010 3
1(
0&
#1650000
b10011010010 !
b10011010010 ,
b10011010010 /
1&
#1660000
b10011 4
0(
0&
#1670000
1&
#1680000
b100011111110000 3
1(
0&
#1690000
b100011111110000 !
b100011111110000 ,
b100011111110000 /
1&
#1700000
b10100 4
0(
0&
#1710000
1&
#1720000
b110011001100001 3
1(
0&
#1730000
b110011001100001 !
b110011001100001 ,
b110011001100001 /
1&
#1740000
b10101 4
0(
0&
#1750000
1&
#1760000
b11001100110000 3
1(
0&
#1770000
b11001100110000 !
b11001100110000 ,
b11001100110000 /
1&
#1780000
b10110 4
0(
0&
#1790000
1&
#1800000
b101110000000001 3
1(
0&
#1810000
b101110000000001 !
b101110000000001 ,
b101110000000001 /
1&
#1820000
b10111 4
0(
0&
#1830000
1&
#1840000
b10111000000000 3
1(
0&
#1850000
b10111000000000 !
b10111000000000 ,
b10111000000000 /
1&
#1860000
b11000 4
0(
0&
#1870000
1&
#1880000
b101001010011001 3
1(
0&
#1890000
b101001010011001 !
b101001010011001 ,
b101001010011001 /
1&
#1900000
b11001 4
0(
0&
#1910000
1&
#1920000
b10100101001100 3
1(
0&
#1930000
b10100101001100 !
b10100101001100 ,
b10100101001100 /
1&
#1940000
b11010 4
0(
0&
#1950000
1&
#1960000
b101000100111111 3
1(
0&
#1970000
b101000100111111 !
b101000100111111 ,
b101000100111111 /
1&
#1980000
b11011 4
0(
0&
#1990000
1&
#2000000
b10100010011111 3
1(
0&
#2010000
b10100010011111 !
b10100010011111 ,
b10100010011111 /
1&
#2020000
b11100 4
0(
0&
#2030000
1&
#2040000
b1010001001111 3
1(
0&
#2050000
b1010001001111 !
b1010001001111 ,
b1010001001111 /
1&
#2060000
b11101 4
0(
0&
#2070000
1&
#2080000
b101000100111 3
1(
0&
#2090000
b101000100111 !
b101000100111 ,
b101000100111 /
1&
#2100000
b11110 4
0(
0&
#2110000
1&
#2120000
b10100010011 3
1(
0&
#2130000
b10100010011 !
b10100010011 ,
b10100010011 /
1&
#2140000
b11111 4
0(
0&
#2150000
1&
#2160000
b1010001001 3
1(
0&
#2170000
b1010001001 !
b1010001001 ,
b1010001001 /
1&
#2180000
b100000 4
0(
0&
#2190000
1&
#2200000
b101000100 3
1(
0&
#2210000
b101000100 !
b101000100 ,
b101000100 /
1&
#2220000
b100001 4
0(
0&
#2230000
1&
#2240000
b100010100111011 3
1(
0&
#2250000
b100010100111011 !
b100010100111011 ,
b100010100111011 /
1&
#2260000
b100010 4
0(
0&
#2270000
1&
#2280000
b10001010011101 3
1(
0&
#2290000
b10001010011101 !
b10001010011101 ,
b10001010011101 /
1&
#2300000
b100011 4
0(
0&
#2310000
1&
#2320000
b1000101001110 3
1(
0&
#2330000
b1000101001110 !
b1000101001110 ,
b1000101001110 /
1&
#2340000
b100100 4
0(
0&
#2350000
1&
#2360000
b100110100111110 3
1(
0&
#2370000
b100110100111110 !
b100110100111110 ,
b100110100111110 /
1&
#2380000
b100101 4
0(
0&
#2390000
1&
#2400000
b110001100000110 3
1(
0&
#2410000
b110001100000110 !
b110001100000110 ,
b110001100000110 /
1&
#2420000
b100110 4
0(
0&
#2430000
1&
#2440000
b111010000011010 3
1(
0&
#2450000
b111010000011010 !
b111010000011010 ,
b111010000011010 /
1&
#2460000
b100111 4
0(
0&
#2470000
1&
#2480000
b111111110010100 3
1(
0&
#2490000
b111111110010100 !
b111111110010100 ,
b111111110010100 /
1&
#2500000
b101000 4
0(
0&
#2510000
1&
#2520000
b111101001010011 3
1(
0&
#2530000
b111101001010011 !
b111101001010011 ,
b111101001010011 /
1&
#2540000
b101001 4
0(
0&
#2550000
1&
#2560000
b11110100101001 3
1(
0&
#2570000
b11110100101001 !
b11110100101001 ,
b11110100101001 /
1&
#2580000
b101010 4
0(
0&
#2590000
1&
#2600000
b1111010010100 3
1(
0&
#2610000
b1111010010100 !
b1111010010100 ,
b1111010010100 /
1&
#2620000
b101011 4
0(
0&
#2630000
1&
#2640000
b100101011010011 3
1(
0&
#2650000
b100101011010011 !
b100101011010011 ,
b100101011010011 /
1&
#2660000
b101100 4
0(
0&
#2670000
1&
#2680000
b10010101101001 3
1(
0&
#2690000
b10010101101001 !
b10010101101001 ,
b10010101101001 /
1&
#2700000
b101101 4
0(
0&
#2710000
1&
#2720000
b1001010110100 3
1(
0&
#2730000
b1001010110100 !
b1001010110100 ,
b1001010110100 /
1&
#2740000
b101110 4
0(
0&
#2750000
1&
#2760000
b100110011000011 3
1(
0&
#2770000
b100110011000011 !
b100110011000011 ,
b100110011000011 /
1&
#2780000
b101111 4
0(
0&
#2790000
1&
#2800000
b10011001100001 3
1(
0&
#2810000
b10011001100001 !
b10011001100001 ,
b10011001100001 /
1&
#2820000
b110000 4
0(
0&
#2830000
1&
#2840000
b1001100110000 3
1(
0&
#2850000
b1001100110000 !
b1001100110000 ,
b1001100110000 /
1&
#2860000
b110001 4
0(
0&
#2870000
1&
#2880000
b100110000000001 3
1(
0&
#2890000
b100110000000001 !
b100110000000001 ,
b100110000000001 /
1&
#2900000
b110010 4
0(
0&
#2910000
1&
#2920000
b10011000000000 3
1(
0&
#2930000
b10011000000000 !
b10011000000000 ,
b10011000000000 /
1&
#2940000
b110011 4
0(
0&
#2950000
1&
#2960000
b101011010011001 3
1(
0&
#2970000
b101011010011001 !
b101011010011001 ,
b101011010011001 /
1&
#2980000
b110100 4
0(
0&
#2990000
1&
#3000000
b10101101001100 3
1(
0&
#3010000
b10101101001100 !
b10101101001100 ,
b10101101001100 /
1&
#3020000
b110101 4
0(
0&
#3030000
1&
#3040000
b101000000111111 3
1(
0&
#3050000
b101000000111111 !
b101000000111111 ,
b101000000111111 /
1&
#3060000
b110110 4
0(
0&
#3070000
1&
#3080000
b10100000011111 3
1(
0&
#3090000
b10100000011111 !
b10100000011111 ,
b10100000011111 /
1&
#3100000
b110111 4
0(
0&
#3110000
1&
#3120000
b1010000001111 3
1(
0&
#3130000
b1010000001111 !
b1010000001111 ,
b1010000001111 /
1&
#3140000
b111000 4
0(
0&
#3150000
1&
#3160000
b101000000111 3
1(
0&
#3170000
b101000000111 !
b101000000111 ,
b101000000111 /
1&
#3180000
b111001 4
0(
0&
#3190000
1&
#3200000
b10100000011 3
1(
0&
#3210000
b10100000011 !
b10100000011 ,
b10100000011 /
1&
#3220000
b111010 4
0(
0&
#3230000
1&
#3240000
b1010000001 3
1(
0&
#3250000
b1010000001 !
b1010000001 ,
b1010000001 /
1&
#3260000
b111011 4
0(
0&
#3270000
1&
#3280000
b101000000 3
1(
0&
#3290000
b101000000 !
b101000000 ,
b101000000 /
1&
#3300000
b111100 4
0(
0&
#3310000
1&
#3320000
b100010100111001 3
1(
0&
#3330000
b100010100111001 !
b100010100111001 ,
b100010100111001 /
1&
#3340000
b111101 4
0(
0&
#3350000
1&
#3360000
b10001010011100 3
1(
0&
#3370000
b10001010011100 !
b10001010011100 ,
b10001010011100 /
1&
#3380000
b111110 4
0(
0&
#3390000
1&
#3400000
b101010011010111 3
1(
0&
#3410000
b101010011010111 !
b101010011010111 ,
b101010011010111 /
1&
#3420000
b111111 4
0(
0&
#3430000
1&
#3440000
b10101001101011 3
1(
0&
#3450000
b10101001101011 !
b10101001101011 ,
b10101001101011 /
1&
#3460000
b0 3
b100100011010001010110011110001001101010111100110111101111 1
b1000000 4
0(
0&
#3470000
1&
#3480000
1'
0&
#3490000
b0 !
b0 ,
b0 /
1&
#3500000
02
b0 4
0'
0&
#3510000
1&
#3520000
1(
0$
0&
#3530000
1&
#3540000
b1 4
0(
0&
#3550000
1&
#3560000
1(
0&
#3570000
1&
#3580000
b10 4
0(
0&
#3590000
1&
#3600000
1(
0&
#3610000
1&
#3620000
b11 4
0(
0&
#3630000
1&
#3640000
1(
0&
#3650000
1&
#3660000
b100 4
0(
0&
#3670000
1&
#3680000
1(
0&
#3690000
1&
#3700000
b101 4
0(
0&
#3710000
1&
#3720000
1(
0&
#3730000
1&
#3740000
b110 4
0(
0&
#3750000
1&
#3760000
1(
0&
#3770000
1&
#3780000
12
b111 4
0(
0&
#3790000
1&
#3800000
b100010110011001 3
1(
1$
0&
#3810000
b100010110011001 !
b100010110011001 ,
b100010110011001 /
1&
#3820000
02
b1000 4
0(
0&
#3830000
1&
#3840000
b110011101010101 3
1(
0$
0&
#3850000
b110011101010101 !
b110011101010101 ,
b110011101010101 /
1&
#3860000
b1001 4
0(
0&
#3870000
1&
#3880000
b111011000110011 3
1(
0&
#3890000
b111011000110011 !
b111011000110011 ,
b111011000110011 /
1&
#3900000
12
b1010 4
0(
0&
#3910000
1&
#3920000
b11101100011001 3
1(
1$
0&
#3930000
b11101100011001 !
b11101100011001 ,
b11101100011001 /
1&
#3940000
02
b1011 4
0(
0&
#3950000
1&
#3960000
b101100000010101 3
1(
0$
0&
#3970000
b101100000010101 !
b101100000010101 ,
b101100000010101 /
1&
#3980000
b1100 4
0(
0&
#3990000
1&
#4000000
b110100110010011 3
1(
0&
#4010000
b110100110010011 !
b110100110010011 ,
b110100110010011 /
1&
#4020000
b1101 4
0(
0&
#4030000
1&
#4040000
b111000101010000 3
1(
0&
#4050000
b111000101010000 !
b111000101010000 ,
b111000101010000 /
1&
#4060000
12
b1110 4
0(
0&
#4070000
1&
#4080000
b111110100110001 3
1(
1$
0&
#4090000
b111110100110001 !
b111110100110001 ,
b111110100110001 /
1&
#4100000
b1111 4
0(
0&
#4110000
1&
#4120000
b11111010011000 3
1(
0&
#4130000
b11111010011000 !
b11111010011000 ,
b11111010011000 /
1&
#4140000
02
b10000 4
0(
0&
#4150000
1&
#4160000
b1111101001100 3
1(
0$
0&
#4170000
b1111101001100 !
b1111101001100 ,
b1111101001100 /
1&
#4180000
12
b10001 4
0(
0&
#4190000
1&
#4200000
b100101000111111 3
1(
1$
0&
#4210000
b100101000111111 !
b100101000111111 ,
b100101000111111 /
1&
#4220000
02
b10010 4
0(
0&
#4230000
1&
#4240000
b110000010000110 3
1(
0$
0&
#4250000
b110000010000110 !
b110000010000110 ,
b110000010000110 /
1&
#4260000
b10011 4
0(
0&
#4270000
1&
#4280000
b11000001000011 3
1(
0&
#4290000
b11000001000011 !
b11000001000011 ,
b11000001000011 /
1&
#4300000
b10100 4
0(
0&
#4310000
1&
#4320000
b101110110111000 3
1(
0&
#4330000
b101110110111000 !
b101110110111000 ,
b101110110111000 /
1&
#4340000
12
b10101 4
0(
0&
#4350000
1&
#4360000
b110101101000101 3
1(
1$
0&
#4370000
b110101101000101 !
b110101101000101 ,
b110101101000101 /
1&
#4380000
02
b10110 4
0(
0&
#4390000
1&
#4400000
b111000000111011 3
1(
0$
0&
#4410000
b111000000111011 !
b111000000111011 ,
b111000000111011 /
1&
#4420000
12
b10111 4
0(
0&
#4430000
1&
#4440000
b11100000011101 3
1(
1$
0&
#4450000
b11100000011101 !
b11100000011101 ,
b11100000011101 /
1&
#4460000
02
b11000 4
0(
0&
#4470000
1&
#4480000
b101100110010111 3
1(
0$
0&
#4490000
b101100110010111 !
b101100110010111 ,
b101100110010111 /
1&
#4500000
12
b11001 4
0(
0&
#4510000
1&
#4520000
b10110011001011 3
1(
1$
0&
#4530000
b10110011001011 !
b10110011001011 ,
b10110011001011 /
1&
#4540000
b11010 4
0(
0&
#4550000
1&
#4560000
b1011001100101 3
1(
0&
#4570000
b1011001100101 !
b1011001100101 ,
b1011001100101 /
1&
#4580000
02
b11011 4
0(
0&
#4590000
1&
#4600000
b100111010101011 3
1(
0$
0&
#4610000
b100111010101011 !
b100111010101011 ,
b100111010101011 /
1&
#4620000
b11100 4
0(
0&
#4630000
1&
#4640000
b110001011001100 3
1(
0&
#4650000
b110001011001100 !
b110001011001100 ,
b110001011001100 /
1&
#4660000
12
b11101 4
0(
0&
#4670000
1&
#4680000
b111010011111111 3
1(
1$
0&
#4690000
b111010011111111 !
b111010011111111 ,
b111010011111111 /
1&
#4700000
b11110 4
0(
0&
#4710000
1&
#4720000
b11101001111111 3
1(
0&
#4730000
b11101001111111 !
b11101001111111 ,
b11101001111111 /
1&
#4740000
b11111 4
0(
0&
#4750000
1&
#4760000
b1110100111111 3
1(
0&
#4770000
b1110100111111 !
b1110100111111 ,
b1110100111111 /
1&
#4780000
b100000 4
0(
0&
#4790000
1&
#4800000
b111010011111 3
1(
0&
#4810000
b111010011111 !
b111010011111 ,
b111010011111 /
1&
#4820000
02
b100001 4
0(
0&
#4830000
1&
#4840000
b100001011010110 3
1(
0$
0&
#4850000
b100001011010110 !
b100001011010110 ,
b100001011010110 /
1&
#4860000
b100010 4
0(
0&
#4870000
1&
#4880000
b10000101101011 3
1(
0&
#4890000
b10000101101011 !
b10000101101011 ,
b10000101101011 /
1&
#4900000
b100011 4
0(
0&
#4910000
1&
#4920000
b101010100101100 3
1(
0&
#4930000
b101010100101100 !
b101010100101100 ,
b101010100101100 /
1&
#4940000
12
b100100 4
0(
0&
#4950000
1&
#4960000
b110111100001111 3
1(
1$
0&
#4970000
b110111100001111 !
b110111100001111 ,
b110111100001111 /
1&
#4980000
02
b100101 4
0(
0&
#4990000
1&
#5000000
b111001000011110 3
1(
0$
0&
#5010000
b111001000011110 !
b111001000011110 ,
b111001000011110 /
1&
#5020000
b100110 4
0(
0&
#5030000
1&
#5040000
b11100100001111 3
1(
0&
#5050000
b11100100001111 !
b11100100001111 ,
b11100100001111 /
1&
#5060000
12
b100111 4
0(
0&
#5070000
1&
#5080000
b1110010000111 3
1(
1$
0&
#5090000
b1110010000111 !
b1110010000111 ,
b1110010000111 /
1&
#5100000
b101000 4
0(
0&
#5110000
1&
#5120000
b111001000011 3
1(
0&
#5130000
b111001000011 !
b111001000011 ,
b111001000011 /
1&
#5140000
02
b101001 4
0(
0&
#5150000
1&
#5160000
b100001010111000 3
1(
0$
0&
#5170000
b100001010111000 !
b100001010111000 ,
b100001010111000 /
1&
#5180000
12
b101010 4
0(
0&
#5190000
1&
#5200000
b110010011000101 3
1(
1$
0&
#5210000
b110010011000101 !
b110010011000101 ,
b110010011000101 /
1&
#5220000
02
b101011 4
0(
0&
#5230000
1&
#5240000
b111011111111011 3
1(
0$
0&
#5250000
b111011111111011 !
b111011111111011 ,
b111011111111011 /
1&
#5260000
12
b101100 4
0(
0&
#5270000
1&
#5280000
b11101111111101 3
1(
1$
0&
#5290000
b11101111111101 !
b11101111111101 ,
b11101111111101 /
1&
#5300000
02
b101101 4
0(
0&
#5310000
1&
#5320000
b101100001100111 3
1(
0$
0&
#5330000
b101100001100111 !
b101100001100111 ,
b101100001100111 /
1&
#5340000
12
b101110 4
0(
0&
#5350000
1&
#5360000
b10110000110011 3
1(
1$
0&
#5370000
b10110000110011 !
b10110000110011 ,
b10110000110011 /
1&
#5380000
b101111 4
0(
0&
#5390000
1&
#5400000
b1011000011001 3
1(
0&
#5410000
b1011000011001 !
b1011000011001 ,
b1011000011001 /
1&
#5420000
b110000 4
0(
0&
#5430000
1&
#5440000
b101100001100 3
1(
0&
#5450000
b101100001100 !
b101100001100 ,
b101100001100 /
1&
#5460000
b110001 4
0(
0&
#5470000
1&
#5480000
b100000000011111 3
1(
0&
#5490000
b100000000011111 !
b100000000011111 ,
b100000000011111 /
1&
#5500000
02
b110010 4
0(
0&
#5510000
1&
#5520000
b110010110010110 3
1(
0$
0&
#5530000
b110010110010110 !
b110010110010110 ,
b110010110010110 /
1&
#5540000
b110011 4
0(
0&
#5550000
1&
#5560000
b11001011001011 3
1(
0&
#5570000
b11001011001011 !
b11001011001011 ,
b11001011001011 /
1&
#5580000
12
b110100 4
0(
0&
#5590000
1&
#5600000
b1100101100101 3
1(
1$
0&
#5610000
b1100101100101 !
b1100101100101 ,
b1100101100101 /
1&
#5620000
b110101 4
0(
0&
#5630000
1&
#5640000
b110010110010 3
1(
0&
#5650000
b110010110010 !
b110010110010 ,
b110010110010 /
1&
#5660000
02
b110110 4
0(
0&
#5670000
1&
#5680000
b11001011001 3
1(
0$
0&
#5690000
b11001011001 !
b11001011001 ,
b11001011001 /
1&
#5700000
12
b110111 4
0(
0&
#5710000
1&
#5720000
b1100101100 3
1(
1$
0&
#5730000
b1100101100 !
b1100101100 ,
b1100101100 /
1&
#5740000
b111000 4
0(
0&
#5750000
1&
#5760000
b100010000001111 3
1(
0&
#5770000
b100010000001111 !
b100010000001111 ,
b100010000001111 /
1&
#5780000
b111001 4
0(
0&
#5790000
1&
#5800000
b10001000000111 3
1(
0&
