rtl/can_fifo.sv
//-----------------------------------------------------------------------------
// can_fifo
// FIFO síncrono genérico (message-based), usado para Tx e Rx.
// Semântica FWFT (first-word-fall-through): rdata sempre mostra o topo
// quando !empty; pop avança o ponteiro (síncrono).
//-----------------------------------------------------------------------------
module can_fifo #(
    parameter int MSG_W = 99,
    parameter int DEPTH  = 8,
    localparam int PTR_W = (DEPTH <= 1) ? 1 : $clog2(DEPTH)
)(
    input  logic             clk,
    input  logic             rst_n,

    // porta de escrita
    input  logic             push,
    input  logic [MSG_W-1:0] wdata,
    output logic             full,

    // porta de leitura
    input  logic             pop,
    output logic [MSG_W-1:0] rdata,
    output logic             empty,
    output logic             rdata_valid,   // = !empty (topo válido)

    // status
    output logic [PTR_W:0]   count
);

    logic [MSG_W-1:0] mem [DEPTH];
    logic [PTR_W-1:0] wr_ptr, rd_ptr;
    logic [PTR_W:0]   count_r;

    assign full        = (count_r == DEPTH);
    assign empty       = (count_r == 0);
    assign rdata       = mem[rd_ptr];
    assign rdata_valid = !empty;
    assign count       = count_r;

    wire do_push = push && !full;
    wire do_pop  = pop  && !empty;

    always_ff @(posedge clk or negedge rst_n) begin
        if (!rst_n) begin
            wr_ptr  <= '0;
            rd_ptr  <= '0;
            count_r <= '0;
        end else begin
            if (do_push) begin
                mem[wr_ptr] <= wdata;
                wr_ptr      <= (wr_ptr == DEPTH-1) ? '0 : (wr_ptr + 1'b1);
            end
            if (do_pop) begin
                rd_ptr <= (rd_ptr == DEPTH-1) ? '0 : (rd_ptr + 1'b1);
            end
            case ({do_push, do_pop})
                2'b10:   count_r <= count_r + 1'b1;
                2'b01:   count_r <= count_r - 1'b1;
                default: count_r <= count_r;
            endcase
        end
    end

endmodule

uvm/testbench/tb_can_fifo.sv
//-----------------------------------------------------------------------------
// tb_can_fifo — Testbench SIMPLES (smoke test, self-checking, nao-UVM) do
// can_fifo (FWFT message-based, MSG_W=99, DEPTH=8).
//
// Cobre: reset -> empty; push N itens -> count/full; FWFT (rdata == topo
// antes do pop); pop -> count/empty; push+pop simultaneo; drop em full;
// no-op em empty.
//
// Rodar (Xcelium, a partir da raiz):
//   xrun -sv -access +rwc -timescale 1ns/1ps -f script/simlist_can.f \
//        uvm/testbench/tb_can_fifo.sv
// Syntax-check Icarus:
//   iverilog -g2012 -t null -f script/simlist_can.f uvm/testbench/tb_can_fifo.sv
//-----------------------------------------------------------------------------
`timescale 1ns/1ps

module tb_can_fifo;

    localparam int MSG_W  = 99;
    localparam int DEPTH  = 8;

    logic             clk = 1'b0;
    logic             rst_n;
    logic             push, pop;
    logic [MSG_W-1:0] wdata;
    logic [MSG_W-1:0] rdata;
    logic             full, empty, rdata_valid;
    logic [$clog2(DEPTH+1):0] count;   // PTR_W+1 largura do count

    can_fifo #(.MSG_W(MSG_W), .DEPTH(DEPTH)) DUT (
        .clk(clk), .rst_n(rst_n),
        .push(push), .wdata(wdata), .full(full),
        .pop(pop), .rdata(rdata), .empty(empty), .rdata_valid(rdata_valid),
        .count(count)
    );

    always #10 clk = ~clk;

    integer errors;
    logic [MSG_W-1:0] exp_top;   // valor esperado no topo (FWFT)

    // empurra 1 item por ciclo (síncrono); wdata é o "tag" do item
    task do_push(input logic [MSG_W-1:0] d);
        begin
            @(negedge clk);
            push = 1'b1; wdata = d;
            @(negedge clk);
            push = 1'b0;
        end
    endtask

    task do_pop;
        begin
            @(negedge clk);
            pop = 1'b1;
            @(negedge clk);
            pop = 1'b0;
        end
    endtask

    task chk(input bit cond, input string msg);
        begin
            if (!cond) begin
                errors = errors + 1;
                $display("[TB] FAIL: %s", msg);
            end else begin
                $display("[TB] OK:   %s", msg);
            end
        end
    endtask

    initial begin
        $timeformat(-9, 3, " ns", 12);
        errors = 0;
        push = 1'b0; pop = 1'b0; wdata = '0;

        $dumpfile("tb_can_fifo.vcd");
        $dumpvars(0, tb_can_fifo);

        // Reset
        rst_n = 1'b0;
        repeat (3) @(posedge clk);
        rst_n = 1'b1;
        @(posedge clk);

        $display("==========================================================");
        $display("[TB] tb_can_fifo — smoke test");
        $display("==========================================================");

        // 1) Pós-reset: empty=1, count=0, full=0
        chk(empty === 1'b1,            "empty=1 pos-reset");
        chk(full  === 1'b0,            "full=0  pos-reset");
        chk(count == 0,                "count=0 pos-reset");
        chk(rdata_valid === 1'b0,      "rdata_valid=0 pos-reset");

        // 2) Push 8 itens (enche). tag = i (larga em [7:0], resto zero)
        for (int i = 0; i < DEPTH; i++) begin
            do_push({92'b0, 7'b0, i[7:0]});  // wdata[7:0] = i
        end
        @(posedge clk);
        chk(full  === 1'b1,            "full=1 apos encher");
        chk(empty === 1'b0,            "empty=0 apos encher");
        chk(count == DEPTH,            "count=DEPTH apos encher");

        // 3) Push em full -> drop, count não muda
        do_push({99{1'b1}});
        @(posedge clk);
        chk(full === 1'b1,             "full persiste apos push em full");
        chk(count == DEPTH,            "count nao muda apos push em full");

        // 4) FWFT: topo agora é o item 0 (wdata[7:0]=0)
        chk(rdata[7:0] === 8'd0,       "FWFT: rdata == item 0 (topo)");
        chk(rdata_valid === 1'b1,      "rdata_valid=1 com topo valido");

        // 5) Pop todos, conferindo ordem FIFO (item 0,1,2,...,7)
        for (int i = 0; i < DEPTH; i++) begin
            // FWFT: rdata já é o topo ANTES do pop
            chk(rdata[7:0] === i[7:0], $sformatf("pop %0d: rdata == item %0d", i, i));
            do_pop;
            @(posedge clk);
        end
        chk(empty === 1'b1,            "empty=1 apos esvaziar");
        chk(count == 0,                "count=0 apos esvaziar");
        chk(rdata_valid === 1'b0,      "rdata_valid=0 apos esvaziar");

        // 6) Pop em empty -> no-op
        do_pop;
        @(posedge clk);
        chk(empty === 1'b1,            "empty persiste apos pop em empty");
        chk(count == 0,                "count=0 apos pop em empty");

        // 7) Push + Pop simultâneo (count mantém com 1 item)
        //    Antes garante count=1; então push+pop -> do_push=1, do_pop=1,
        //    count não muda.
        do_push({91'b0, 8'hAA});        // count de 0 -> 1
        @(posedge clk);
        chk(count == 1,                 "precondicao: count=1");
        @(negedge clk);
        push = 1'b1; pop = 1'b1; wdata = {91'b0, 8'hAB};
        @(negedge clk);
        push = 1'b0; pop = 1'b0;
        @(posedge clk);
        chk(count == 1,                 "push+pop simultaneo mantem count=1");

        // 8) Esvazia e faz 1 push isolado, confere FWFT
        do_pop;                         // count de 1 -> 0
        @(posedge clk);
        chk(count == 0,                 "precondicao: count=0 apos pop");
        do_push({91'b0, 8'hAB});
        @(posedge clk);
        chk(rdata[7:0] === 8'hAB,       "apos 1 push: rdata == 0xAB");
        chk(count == 1,                 "count=1 apos 1 push");

        // --------------------------------------------------
        $display("----------------------------------------------------------");
        if (errors == 0) $display("[TB] ===== SMOKE TEST PASS =====");
        else             $display("[TB] ===== SMOKE TEST FAIL (%0d erros) =====", errors);
        $display("----------------------------------------------------------");
        $finish;
    end

    initial begin
        #1ms;
        $display("[TB] TIMEOUT global (1 ms). Abortando.");
        $finish;
    end

endmodule

vcd files/tb_can_fifo.vcd
$date
	Tue Jul 07 22:07:18 2026
$end
$version
	Icarus Verilog
$end
$timescale
	1ps
$end
$scope module tb_can_fifo $end
$var wire 1 ! rdata_valid $end
$var wire 99 " rdata [98:0] $end
$var wire 1 # full $end
$var wire 1 $ empty $end
$var wire 5 % count [4:0] $end
$var parameter 32 & DEPTH $end
$var parameter 32 ' MSG_W $end
$var reg 1 ( clk $end
$var reg 1 ) pop $end
$var reg 1 * push $end
$var reg 1 + rst_n $end
$var reg 99 , wdata [98:0] $end
$var integer 32 - errors [31:0] $end
$scope module DUT $end
$var wire 1 ( clk $end
$var wire 4 . count [3:0] $end
$var wire 1 / do_pop $end
$var wire 1 0 do_push $end
$var wire 1 ) pop $end
$var wire 1 * push $end
$var wire 99 1 rdata [98:0] $end
$var wire 1 + rst_n $end
$var wire 99 2 wdata [98:0] $end
$var wire 1 ! rdata_valid $end
$var wire 1 # full $end
$var wire 1 $ empty $end
$var parameter 32 3 DEPTH $end
$var parameter 32 4 MSG_W $end
$var parameter 32 5 PTR_W $end
$var reg 4 6 count_r [3:0] $end
$var reg 3 7 rd_ptr [2:0] $end
$var reg 3 8 wr_ptr [2:0] $end
$upscope $end
$scope begin $ivl_for_loop0 $end
$var integer 32 9 i [31:0] $end
$upscope $end
$scope begin $ivl_for_loop1 $end
$var integer 32 : i [31:0] $end
$upscope $end
$scope task chk $end
$var reg 1 ; cond $end
$upscope $end
$scope task do_pop $end
$upscope $end
$scope task do_push $end
$var reg 99 < d [98:0] $end
$upscope $end
$upscope $end
$enddefinitions $end
$comment Show the parameter values. $end
$dumpall
b11 5
b1100011 4
b1000 3
b1100011 '
b1000 &
$end
#0
$dumpvars
bx <
0;
b0 :
b0 9
b0 8
b0 7
b0 6
b0 2
bx 1
00
0/
b0 .
b0 -
b0 ,
0+
0*
0)
0(
b0 %
1$
0#
bx "
0!
$end
#10000
1(
#20000
0(
#30000
1(
#40000
0(
#50000
1+
1(
#60000
0(
#70000
b0 <
1;
1(
#80000
10
1*
0(
#90000
1!
0$
b1 %
b1 .
b1 6
b1 8
b0 "
b0 1
1(
#100000
00
b1 <
b1 9
0*
0(
#110000
1(
#120000
10
b1 ,
b1 2
1*
0(
#130000
b10 %
b10 .
b10 6
b10 8
1(
#140000
00
b10 <
b10 9
0*
0(
#150000
1(
#160000
10
b10 ,
b10 2
1*
0(
#170000
b11 %
b11 .
b11 6
b11 8
1(
#180000
00
b11 <
b11 9
0*
0(
#190000
1(
#200000
10
b11 ,
b11 2
1*
0(
#210000
b100 %
b100 .
b100 6
b100 8
1(
#220000
00
b100 <
b100 9
0*
0(
#230000
1(
#240000
10
b100 ,
b100 2
1*
0(
#250000
b101 %
b101 .
b101 6
b101 8
1(
#260000
00
b101 <
b101 9
0*
0(
#270000
1(
#280000
10
b101 ,
b101 2
1*
0(
#290000
b110 %
b110 .
b110 6
b110 8
1(
#300000
00
b110 <
b110 9
0*
0(
#310000
1(
#320000
10
b110 ,
b110 2
1*
0(
#330000
b111 %
b111 .
b111 6
b111 8
1(
#340000
00
b111 <
b111 9
0*
0(
#350000
1(
#360000
10
b111 ,
b111 2
1*
0(
#370000
00
1#
b1000 %
b1000 .
b1000 6
b0 8
1(
#380000
b1000 9
0*
0(
#390000
b111111111111111111111111111111111111111111111111111111111111111111111111111111111111111111111111111 <
1(
#400000
b111111111111111111111111111111111111111111111111111111111111111111111111111111111111111111111111111 ,
b111111111111111111111111111111111111111111111111111111111111111111111111111111111111111111111111111 2
1*
0(
#410000
1(
#420000
0*
0(
#430000
1(
#440000
1/
1)
0(
#450000
0#
b111 %
b111 .
b111 6
b1 "
b1 1
b1 7
1(
#460000
0/
0)
0(
#470000
b1 :
1(
#480000
1/
1)
0(
#490000
b110 %
b110 .
b110 6
b10 "
b10 1
b10 7
1(
#500000
0/
0)
0(
#510000
b10 :
1(
#520000
1/
1)
0(
#530000
b101 %
b101 .
b101 6
b11 "
b11 1
b11 7
1(
#540000
0/
0)
0(
#550000
b11 :
1(
#560000
1/
1)
0(
#570000
b100 %
b100 .
b100 6
b100 "
b100 1
b100 7
1(
#580000
0/
0)
0(
#590000
b100 :
1(
#600000
1/
1)
0(
#610000
b11 %
b11 .
b11 6
b101 "
b101 1
b101 7
1(
#620000
0/
0)
0(
#630000
b101 :
1(
#640000
1/
1)
0(
#650000
b10 %
b10 .
b10 6
b110 "
b110 1
b110 7
1(
#660000
0/
0)
0(
#670000
b110 :
1(
#680000
1/
1)
0(
#690000
b1 %
b1 .
b1 6
b111 "
b111 1
b111 7
1(
#700000
0/
0)
0(
#710000
b111 :
1(
#720000
1/
1)
0(
#730000
0/
0!
1$
b0 %
b0 .
b0 6
b0 "
b0 1
b0 7
1(
#740000
0)
0(
#750000
b1000 :
1(
#760000
1)
0(
#770000
1(
#780000
0)
0(
#790000
b10101010 <
1(
#800000
10
b10101010 ,
b10101010 2
1*
0(
#810000
1!
0$
b1 %
b1 .
b1 6
b1 8
b10101010 "
b10101010 1
1(
#820000
00
0*
0(
#830000
1(
#840000
1/
10
b10101011 ,
b10101011 2
1)
1*
0(
#850000
b10101011 "
b10101011 1
b1 7
b10 8
1(
#860000
0/
00
0)
0*
0(
#870000
1(
#880000
1/
1)
0(
#890000
0/
0!
1$
b0 %
b0 .
b0 6
b10 "
b10 1
b10 7
1(
#900000
0)
0(
#910000
b10101011 <
1(
#920000
10
1*
0(
#930000
1!
0$
b1 %
b1 .
b1 6
b11 8
b10101011 "
b10101011 1
1(
#940000
00
0*
0(
