rtl/can_error.sv
//-----------------------------------------------------------------------------
// can_error  (Error Management Logic - EML)
// Mantém TEC e REC segundo ISO 11898-1 (versão de regras principais) e deriva
// os estados Error Active / Error Passive / Bus Off.
//
// Regras implementadas (simplificação documentada da ISO; ajuste fino guiado
// pela verificação UVM dirigida):
//   - erro como TRANSMISSOR (tx_context=1):  TEC += 8
//   - erro como RECEPTOR   (tx_context=0):   REC += 1
//   - frame TX bem-sucedido:                 TEC -= 1 (se 0 < TEC < 256)
//   - frame RX bem-sucedido:                 REC -= 1 (se REC > 0)
//   - Bus Off quando TEC >= 256; recuperação via err_reset (TEC=REC=0)
//   - arb_lost NÃO conta como erro (informativo).
// TEC interno 9 bits para detectar 256; REC 8 bits saturando em 0xFF.
//-----------------------------------------------------------------------------
module can_error (
    input  logic        clk,
    input  logic        rst_n,

    // eventos de erro (do FSM)
    input  logic        bit_error,
    input  logic        stuff_error,
    input  logic        crc_error,
    input  logic        ack_error,
    input  logic        form_error,

    // contexto (do FSM)
    input  logic        tx_context,      // 1 = erro em TX, 0 = em RX
    input  logic        arb_lost,        // não conta como erro (informativo)

    // sucesso
    input  logic        frame_tx_ok,
    input  logic        frame_rx_ok,

    // controle
    input  logic        err_reset,       // SFT_RST / início de recuperação Bus Off

    // contadores
    output logic [7:0]  tec,
    output logic [7:0]  rec,

    // estado
    output logic        error_active,
    output logic        error_passive,
    output logic        bus_off,

    // gatilho de Error Frame
    output logic        error_flag_req
);

    logic [8:0] tec_int;   // 9 bits: 0..256
    logic [7:0] rec_int;

    wire any_err = bit_error | stuff_error | crc_error | ack_error | form_error;

    always_ff @(posedge clk or negedge rst_n) begin
        if (!rst_n) begin
            tec_int <= 9'd0;
            rec_int <= 8'd0;
        end else if (err_reset) begin
            tec_int <= 9'd0;
            rec_int <= 8'd0;
        end else begin
            // ---- TEC ----
            if (any_err && tx_context) begin
                tec_int <= (tec_int + 9'd8 > 9'd256) ? 9'd256 : (tec_int + 9'd8);
            end else if (frame_tx_ok && (tec_int > 9'd0) && (tec_int < 9'd256)) begin
                tec_int <= tec_int - 9'd1;
            end

            // ---- REC ----
            if (any_err && !tx_context) begin
                rec_int <= (rec_int == 8'hFF) ? 8'hFF : (rec_int + 8'd1);
            end else if (frame_rx_ok && (rec_int > 8'd0)) begin
                rec_int <= rec_int - 8'd1;
            end
        end
    end

    assign tec            = tec_int[7:0];
    assign rec            = rec_int;
    assign bus_off        = (tec_int >= 9'd256);
    assign error_passive  = (tec_int >= 9'd128) || (rec_int >= 8'd128);
    assign error_active   = !bus_off && !error_passive;
    assign error_flag_req = any_err;

    // arb_lost é intencionalmente não usado na contagem (ISO: não é erro).
    wire _unused = arb_lost;

endmodule

uvm/testbench/tb_can_error.sv
//-----------------------------------------------------------------------------
// tb_can_error — Testbench SIMPLES (smoke test, self-checking, nao-UVM) do
// can_error (EML: TEC/REC ISO, Error Active/Passive/Bus Off).
//
// Regras do RTL:
//   - erro TX (tx_context=1):    TEC += 8 (sat 256)
//   - erro RX (tx_context=0):    REC += 1 (sat 0xFF)
//   - frame_tx_ok:               TEC -= 1 (se 0 < TEC < 256)
//   - frame_rx_ok:               REC -= 1 (se REC > 0)
//   - err_reset:                 TEC=REC=0
//   - bus_off:                   TEC >= 256
//   - error_passive:             TEC >= 128 || REC >= 128
//
// Cobre:
//   - Incrementos TEC/REC, decrementos, saturações.
//   - Transições de estado Active -> Passive -> Bus Off.
//   - err_reset zera.
//
// Rodar (Xcelium):
//   xrun -sv -access +rwc -timescale 1ns/1ps -f script/simlist_can.f \
//        uvm/testbench/tb_can_error.sv
// Icarus:
//   iverilog -g2012 -t null -f script/simlist_can.f uvm/testbench/tb_can_error.sv
//-----------------------------------------------------------------------------
`timescale 1ns/1ps

module tb_can_error;

    logic        clk = 1'b0;
    logic        rst_n;
    logic        bit_error, stuff_error, crc_error, ack_error, form_error;
    logic        tx_context, arb_lost;
    logic        frame_tx_ok, frame_rx_ok;
    logic        err_reset;
    logic [7:0]  tec, rec;
    logic        error_active, error_passive, bus_off, error_flag_req;

    can_error DUT (
        .clk(clk), .rst_n(rst_n),
        .bit_error(bit_error), .stuff_error(stuff_error), .crc_error(crc_error),
        .ack_error(ack_error), .form_error(form_error),
        .tx_context(tx_context), .arb_lost(arb_lost),
        .frame_tx_ok(frame_tx_ok), .frame_rx_ok(frame_rx_ok),
        .err_reset(err_reset),
        .tec(tec), .rec(rec),
        .error_active(error_active), .error_passive(error_passive),
        .bus_off(bus_off), .error_flag_req(error_flag_req)
    );

    always #10 clk = ~clk;

    integer errors;

    task chk(input bit cond, input string msg);
        begin
            if (!cond) begin errors = errors + 1; $display("[TB] FAIL: %s", msg); end
            else         $display("[TB] OK:   %s", msg);
        end
    endtask

    // Aplica um pulso de 1 ciclo de um erro TX (default bit_error)
    task tx_err_pulse;
        begin
            @(negedge clk);
            tx_context = 1'b1; bit_error = 1'b1;
            @(negedge clk);
            tx_context = 1'b0; bit_error = 1'b0;
        end
    endtask

    task rx_err_pulse;
        begin
            @(negedge clk);
            tx_context = 1'b0; crc_error = 1'b1;   // qualquer erro em RX
            @(negedge clk);
            crc_error = 1'b0;
        end
    endtask

    task tx_ok_pulse;
        begin
            @(negedge clk); frame_tx_ok = 1'b1;
            @(negedge clk); frame_tx_ok = 1'b0;
        end
    endtask

    task rx_ok_pulse;
        begin
            @(negedge clk); frame_rx_ok = 1'b1;
            @(negedge clk); frame_rx_ok = 1'b0;
        end
    endtask

    initial begin
        $timeformat(-9, 3, " ns", 12);
        errors = 0;
        bit_error = 1'b0; stuff_error = 1'b0; crc_error = 1'b0;
        ack_error = 1'b0; form_error = 1'b0;
        tx_context = 1'b0; arb_lost = 1'b0;
        frame_tx_ok = 1'b0; frame_rx_ok = 1'b0;
        err_reset = 1'b0;

        $dumpfile("tb_can_error.vcd");
        $dumpvars(0, tb_can_error);

        rst_n = 1'b0;
        repeat (3) @(posedge clk);
        rst_n = 1'b1;
        @(posedge clk);

        $display("==========================================================");
        $display("[TB] tb_can_error — smoke test");
        $display("==========================================================");

        // 1) Pós-reset: TEC=0, REC=0, Error Active
        chk(tec === 8'd0,            "tec=0 pos-reset");
        chk(rec === 8'd0,            "rec=0 pos-reset");
        chk(error_active === 1'b1,   "error_active=1 pos-reset");
        chk(error_passive === 1'b0,  "error_passive=0 pos-reset");
        chk(bus_off === 1'b0,        "bus_off=0 pos-reset");

        // 2) Erro TX: TEC += 8
        tx_err_pulse;
        @(posedge clk);
        chk(tec === 8'd8,            "1 erro TX -> TEC=8");
        tx_err_pulse; @(posedge clk);
        chk(tec === 8'd16,           "2 erros TX -> TEC=16");

        // 3) frame_tx_ok: TEC -= 1
        tx_ok_pulse; @(posedge clk);
        chk(tec === 8'd15,           "frame_tx_ok -> TEC=15");

        // 4) Erro RX: REC += 1
        rx_err_pulse; @(posedge clk);
        chk(rec === 8'd1,            "1 erro RX -> REC=1");
        rx_err_pulse; @(posedge clk);
        chk(rec === 8'd2,            "2 erros RX -> REC=2");

        // 5) frame_rx_ok: REC -= 1
        rx_ok_pulse; @(posedge clk);
        chk(rec === 8'd1,            "frame_rx_ok -> REC=1");

        // 6) error_flag_req acompanha any_err
        @(negedge clk); bit_error = 1'b1;
        @(posedge clk);
        #1;
        chk(error_flag_req === 1'b1, "error_flag_req=1 com bit_error");
        @(negedge clk); bit_error = 1'b0;
        @(posedge clk);
        #1;
        chk(error_flag_req === 1'b0, "error_flag_req=0 sem erros");

        // 7) err_reset zera TEC/REC
        @(negedge clk); err_reset = 1'b1;
        @(negedge clk); err_reset = 1'b0;
        @(posedge clk);
        chk(tec === 8'd0,            "err_reset -> TEC=0");
        chk(rec === 8'd0,            "err_reset -> REC=0");
        chk(error_active === 1'b1,   "err_reset -> Error Active");

        // 8) Error Passive: TEC >= 128 (16 erros TX * 8 = 128)
        for (int i = 0; i < 16; i++) tx_err_pulse;
        @(posedge clk);
        chk(tec === 8'd128,          "16 erros TX -> TEC=128");
        chk(error_passive === 1'b1,  "TEC>=128 -> Error Passive");
        chk(error_active === 1'b0,   "Error Active caiu");
        chk(bus_off === 1'b0,        "ainda nao Bus Off");

        // 9) Bus Off: TEC >= 256 (mais 16 erros TX -> 256)
        for (int i = 0; i < 16; i++) tx_err_pulse;
        @(posedge clk);
        chk(bus_off === 1'b1,         "TEC>=256 -> Bus Off");
        chk(error_passive === 1'b1,  "Bus Off -> Passive=1 (precedência)");
        chk(error_active === 1'b0,   "Bus Off -> Active=0");

        // 10) Saturação em 256 (não passa)
        tx_err_pulse; @(posedge clk);
        chk(tec === 8'd0,            "TEC sat 256 interno (output [7:0]=0)");
        chk(bus_off === 1'b1,        "Permanece Bus Off");

        // 11) REC saturação em 0xFF
        @(negedge clk); err_reset = 1'b1;
        @(negedge clk); err_reset = 1'b0; tx_context = 1'b0;
        @(posedge clk);
        for (int i = 0; i < 300; i++) rx_err_pulse;
        @(posedge clk);
        chk(rec === 8'hFF,           "REC satura em 0xFF");
        chk(error_passive === 1'b1,  "REC>=128 -> Passive");

        // 12) err_reset final
        @(negedge clk); err_reset = 1'b1;
        @(negedge clk); err_reset = 1'b0;
        @(posedge clk);
        chk(tec === 8'd0 && rec === 8'd0, "err_reset final zera tudo");
        chk(error_active === 1'b1,        "volta a Error Active");

        $display("----------------------------------------------------------");
        if (errors == 0) $display("[TB] ===== SMOKE TEST PASS =====");
        else             $display("[TB] ===== SMOKE TEST FAIL (%0d erros) =====", errors);
        $display("----------------------------------------------------------");
        $finish;
    end

    initial begin
        #1ms;
        $display("[TB] TIMEOUT global (1 ms). Abortando.");
        $finish;
    end

endmodule

vcd files/tb_can_error.vcd
$date
	Tue Jul 07 22:07:19 2026
$end
$version
	Icarus Verilog
$end
$timescale
	1ps
$end
$scope module tb_can_error $end
$var wire 8 ! tec [7:0] $end
$var wire 8 " rec [7:0] $end
$var wire 1 # error_passive $end
$var wire 1 $ error_flag_req $end
$var wire 1 % error_active $end
$var wire 1 & bus_off $end
$var reg 1 ' ack_error $end
$var reg 1 ( arb_lost $end
$var reg 1 ) bit_error $end
$var reg 1 * clk $end
$var reg 1 + crc_error $end
$var reg 1 , err_reset $end
$var reg 1 - form_error $end
$var reg 1 . frame_rx_ok $end
$var reg 1 / frame_tx_ok $end
$var reg 1 0 rst_n $end
$var reg 1 1 stuff_error $end
$var reg 1 2 tx_context $end
$var integer 32 3 errors [31:0] $end
$scope module DUT $end
$var wire 1 4 _unused $end
$var wire 1 ' ack_error $end
$var wire 1 5 any_err $end
$var wire 1 ( arb_lost $end
$var wire 1 ) bit_error $end
$var wire 1 * clk $end
$var wire 1 + crc_error $end
$var wire 1 , err_reset $end
$var wire 1 % error_active $end
$var wire 1 $ error_flag_req $end
$var wire 1 # error_passive $end
$var wire 1 - form_error $end
$var wire 1 . frame_rx_ok $end
$var wire 1 / frame_tx_ok $end
$var wire 8 6 rec [7:0] $end
$var wire 1 0 rst_n $end
$var wire 1 1 stuff_error $end
$var wire 1 2 tx_context $end
$var wire 8 7 tec [7:0] $end
$var wire 1 & bus_off $end
$var reg 8 8 rec_int [7:0] $end
$var reg 9 9 tec_int [8:0] $end
$upscope $end
$scope begin $ivl_for_loop0 $end
$var integer 32 : i [31:0] $end
$upscope $end
$scope begin $ivl_for_loop1 $end
$var integer 32 ; i [31:0] $end
$upscope $end
$scope begin $ivl_for_loop2 $end
$var integer 32 < i [31:0] $end
$upscope $end
$scope task chk $end
$var reg 1 = cond $end
$upscope $end
$scope task rx_err_pulse $end
$upscope $end
$scope task rx_ok_pulse $end
$upscope $end
$scope task tx_err_pulse $end
$upscope $end
$scope task tx_ok_pulse $end
$upscope $end
$upscope $end
$enddefinitions $end
$comment Show the parameter values. $end
$dumpall
$end
#0
$dumpvars
0=
b0 <
b0 ;
b0 :
b0 9
b0 8
b0 7
b0 6
05
04
b0 3
02
01
00
0/
0.
0-
0,
0+
0*
0)
0(
0'
0&
1%
0$
0#
b0 "
b0 !
$end
#10000
1*
#20000
0*
#30000
1*
#40000
0*
#50000
10
1*
#60000
0*
#70000
1=
1*
#80000
1$
15
1)
12
0*
#90000
b1000 !
b1000 7
b1000 9
1*
#100000
0$
05
0)
02
0*
#110000
1*
#120000
1$
15
1)
12
0*
#130000
b10000 !
b10000 7
b10000 9
1*
#140000
0$
05
0)
02
0*
#150000
1*
#160000
1/
0*
#170000
b1111 !
b1111 7
b1111 9
1*
#180000
0/
0*
#190000
1*
#200000
1$
15
1+
0*
#210000
b1 "
b1 6
b1 8
1*
#220000
0$
05
0+
0*
#230000
1*
#240000
1$
15
1+
0*
#250000
b10 "
b10 6
b10 8
1*
#260000
0$
05
0+
0*
#270000
1*
#280000
1.
0*
#290000
b1 "
b1 6
b1 8
1*
#300000
0.
0*
#310000
1*
#320000
1$
15
1)
0*
#330000
b10 "
b10 6
b10 8
1*
#340000
0$
05
0)
0*
#350000
1*
#360000
1,
0*
#370000
b0 !
b0 7
b0 "
b0 6
b0 8
b0 9
1*
#380000
0,
0*
#390000
1*
#400000
1$
15
1)
12
0*
#410000
b1000 !
b1000 7
b1000 9
1*
#420000
0$
05
b1 :
0)
02
0*
#430000
1*
#440000
1$
15
1)
12
0*
#450000
b10000 !
b10000 7
b10000 9
1*
#460000
0$
05
b10 :
0)
02
0*
#470000
1*
#480000
1$
15
1)
12
0*
#490000
b11000 !
b11000 7
b11000 9
1*
#500000
0$
05
b11 :
0)
02
0*
#510000
1*
#520000
1$
15
1)
12
0*
#530000
b100000 !
b100000 7
b100000 9
1*
#540000
0$
05
b100 :
0)
02
0*
#550000
1*
#560000
1$
15
1)
12
0*
#570000
b101000 !
b101000 7
b101000 9
1*
#580000
0$
05
b101 :
0)
02
0*
#590000
1*
#600000
1$
15
1)
12
0*
#610000
b110000 !
b110000 7
b110000 9
1*
#620000
0$
05
b110 :
0)
02
0*
#630000
1*
#640000
1$
15
1)
12
0*
#650000
b111000 !
b111000 7
b111000 9
1*
#660000
0$
05
b111 :
0)
02
0*
#670000
1*
#680000
1$
15
1)
12
0*
#690000
b1000000 !
b1000000 7
b1000000 9
1*
#700000
0$
05
b1000 :
0)
02
0*
#710000
1*
#720000
1$
15
1)
12
0*
#730000
b1001000 !
b1001000 7
b1001000 9
1*
#740000
0$
05
b1001 :
0)
02
0*
#750000
1*
#760000
1$
15
1)
12
0*
#770000
b1010000 !
b1010000 7
b1010000 9
1*
#780000
0$
05
b1010 :
0)
02
0*
#790000
1*
#800000
1$
15
1)
12
0*
#810000
b1011000 !
b1011000 7
b1011000 9
1*
#820000
0$
05
b1011 :
0)
02
0*
#830000
1*
#840000
1$
15
1)
12
0*
#850000
b1100000 !
b1100000 7
b1100000 9
1*
#860000
0$
05
b1100 :
0)
02
0*
#870000
1*
#880000
1$
15
1)
12
0*
#890000
b1101000 !
b1101000 7
b1101000 9
1*
#900000
0$
05
b1101 :
0)
02
0*
#910000
1*
#920000
1$
15
1)
12
0*
#930000
b1110000 !
b1110000 7
b1110000 9
1*
#940000
0$
05
b1110 :
0)
02
0*
#950000
1*
#960000
1$
15
1)
12
0*
#970000
b1111000 !
b1111000 7
b1111000 9
1*
#980000
0$
05
b1111 :
0)
02
0*
#990000
1*
#1000000
1$
15
1)
12
0*
#1010000
0%
b10000000 !
b10000000 7
1#
b10000000 9
1*
#1020000
0$
05
b10000 :
0)
02
0*
#1030000
1*
#1040000
1$
15
1)
12
0*
#1050000
b10001000 !
b10001000 7
b10001000 9
1*
#1060000
0$
05
b1 ;
0)
02
0*
#1070000
1*
#1080000
1$
15
1)
12
0*
#1090000
b10010000 !
b10010000 7
b10010000 9
1*
#1100000
0$
05
b10 ;
0)
02
0*
#1110000
1*
#1120000
1$
15
1)
12
0*
#1130000
b10011000 !
b10011000 7
b10011000 9
1*
#1140000
0$
05
b11 ;
0)
02
0*
#1150000
1*
#1160000
1$
15
1)
12
0*
#1170000
b10100000 !
b10100000 7
b10100000 9
1*
#1180000
0$
05
b100 ;
0)
02
0*
#1190000
1*
#1200000
1$
15
1)
12
0*
#1210000
b10101000 !
b10101000 7
b10101000 9
1*
#1220000
0$
05
b101 ;
0)
02
0*
#1230000
1*
#1240000
1$
15
1)
12
0*
#1250000
b10110000 !
b10110000 7
b10110000 9
1*
#1260000
0$
05
b110 ;
0)
02
0*
#1270000
1*
#1280000
1$
15
1)
12
0*
#1290000
b10111000 !
b10111000 7
b10111000 9
1*
#1300000
0$
05
b111 ;
0)
02
0*
#1310000
1*
#1320000
1$
15
1)
12
0*
#1330000
b11000000 !
b11000000 7
b11000000 9
1*
#1340000
0$
05
b1000 ;
0)
02
0*
#1350000
1*
#1360000
1$
15
1)
12
0*
#1370000
b11001000 !
b11001000 7
b11001000 9
1*
#1380000
0$
05
b1001 ;
0)
02
0*
#1390000
1*
#1400000
1$
15
1)
12
0*
#1410000
b11010000 !
b11010000 7
b11010000 9
1*
#1420000
0$
05
b1010 ;
0)
02
0*
#1430000
1*
#1440000
1$
15
1)
12
0*
#1450000
b11011000 !
b11011000 7
b11011000 9
1*
#1460000
0$
05
b1011 ;
0)
02
0*
#1470000
1*
#1480000
1$
15
1)
12
0*
#1490000
b11100000 !
b11100000 7
b11100000 9
1*
#1500000
0$
05
b1100 ;
0)
02
0*
#1510000
1*
#1520000
1$
15
1)
12
0*
#1530000
b11101000 !
b11101000 7
b11101000 9
1*
#1540000
0$
05
b1101 ;
0)
02
0*
#1550000
1*
#1560000
1$
15
1)
12
0*
#1570000
b11110000 !
b11110000 7
b11110000 9
1*
#1580000
0$
05
b1110 ;
0)
02
0*
#1590000
1*
#1600000
1$
15
1)
12
0*
#1610000
b11111000 !
b11111000 7
b11111000 9
1*
#1620000
0$
05
b1111 ;
0)
02
0*
#1630000
1*
#1640000
1$
15
1)
12
0*
#1650000
b0 !
b0 7
1&
b100000000 9
1*
#1660000
0$
05
b10000 ;
0)
02
0*
#1670000
1*
#1680000
1$
15
1)
12
0*
#1690000
1*
#1700000
0$
05
0)
02
0*
#1710000
1*
#1720000
1,
0*
#1730000
1%
0#
0&
b0 9
1*
#1740000
0,
0*
#1750000
1*
#1760000
1$
15
1+
0*
#1770000
b1 "
b1 6
b1 8
1*
#1780000
0$
05
b1 <
0+
0*
#1790000
1*
#1800000
1$
15
1+
0*
#1810000
b10 "
b10 6
b10 8
1*
#1820000
0$
05
b10 <
0+
0*
#1830000
1*
#1840000
1$
15
1+
0*
#1850000
b11 "
b11 6
b11 8
1*
#1860000
0$
05
b11 <
0+
0*
#1870000
1*
#1880000
1$
15
1+
0*
#1890000
b100 "
b100 6
b100 8
1*
#1900000
0$
05
b100 <
0+
0*
#1910000
1*
#1920000
1$
15
1+
0*
#1930000
b101 "
b101 6
b101 8
1*
#1940000
0$
05
b101 <
0+
0*
#1950000
1*
#1960000
1$
15
1+
0*
#1970000
b110 "
b110 6
b110 8
1*
#1980000
0$
05
b110 <
0+
0*
#1990000
1*
#2000000
1$
15
1+
0*
#2010000
b111 "
b111 6
b111 8
1*
#2020000
0$
05
b111 <
0+
0*
#2030000
1*
#2040000
1$
15
1+
0*
#2050000
b1000 "
b1000 6
b1000 8
1*
#2060000
0$
05
b1000 <
0+
0*
#2070000
1*
#2080000
1$
15
1+
0*
#2090000
b1001 "
b1001 6
b1001 8
1*
#2100000
0$
05
b1001 <
0+
0*
#2110000
1*
#2120000
1$
15
1+
0*
#2130000
b1010 "
b1010 6
b1010 8
1*
#2140000
0$
05
b1010 <
0+
0*
#2150000
1*
#2160000
1$
15
1+
0*
#2170000
b1011 "
b1011 6
b1011 8
1*
#2180000
0$
05
b1011 <
0+
0*
#2190000
1*
#2200000
1$
15
1+
0*
#2210000
b1100 "
b1100 6
b1100 8
1*
#2220000
0$
05
b1100 <
0+
0*
#2230000
1*
#2240000
1$
15
1+
0*
#2250000
b1101 "
b1101 6
b1101 8
1*
#2260000
0$
05
b1101 <
0+
0*
#2270000
1*
#2280000
1$
15
1+
0*
#2290000
b1110 "
b1110 6
b1110 8
1*
#2300000
0$
05
b1110 <
0+
0*
#2310000
1*
#2320000
1$
15
1+
0*
#2330000
b1111 "
b1111 6
b1111 8
1*
#2340000
0$
05
b1111 <
0+
0*
#2350000
1*
#2360000
1$
15
1+
0*
#2370000
b10000 "
b10000 6
b10000 8
1*
#2380000
0$
05
b10000 <
0+
0*
#2390000
1*
#2400000
1$
15
1+
0*
#2410000
b10001 "
b10001 6
b10001 8
1*
#2420000
0$
05
b10001 <
0+
0*
#2430000
1*
#2440000
1$
15
1+
0*
#2450000
b10010 "
b10010 6
b10010 8
1*
#2460000
0$
05
b10010 <
0+
0*
#2470000
1*
#2480000
1$
15
1+
0*
#2490000
b10011 "
b10011 6
b10011 8
1*
#2500000
0$
05
b10011 <
0+
0*
#2510000
1*
#2520000
1$
15
1+
0*
#2530000
b10100 "
b10100 6
b10100 8
1*
#2540000
0$
05
b10100 <
0+
0*
#2550000
1*
#2560000
1$
15
1+
0*
#2570000
b10101 "
b10101 6
b10101 8
1*
#2580000
0$
05
b10101 <
0+
0*
#2590000
1*
#2600000
1$
15
1+
0*
#2610000
b10110 "
b10110 6
b10110 8
1*
#2620000
0$
05
b10110 <
0+
0*
#2630000
1*
#2640000
1$
15
1+
0*
#2650000
b10111 "
b10111 6
b10111 8
1*
#2660000
0$
05
b10111 <
0+
0*
#2670000
1*
#2680000
1$
15
1+
0*
#2690000
b11000 "
b11000 6
b11000 8
1*
#2700000
0$
05
b11000 <
0+
0*
#2710000
1*
#2720000
1$
15
1+
0*
#2730000
b11001 "
b11001 6
b11001 8
1*
#2740000
0$
05
b11001 <
0+
0*
#2750000
1*
#2760000
1$
15
1+
0*
#2770000
b11010 "
b11010 6
b11010 8
1*
#2780000
0$
05
b11010 <
0+
0*
#2790000
1*
#2800000
1$
15
1+
0*
#2810000
b11011 "
b11011 6
b11011 8
1*
#2820000
0$
05
b11011 <
0+
0*
#2830000
1*
#2840000
1$
15
1+
0*
#2850000
b11100 "
b11100 6
b11100 8
1*
#2860000
0$
05
b11100 <
0+
0*
#2870000
1*
#2880000
1$
15
1+
0*
#2890000
b11101 "
b11101 6
b11101 8
1*
#2900000
0$
05
b11101 <
0+
0*
#2910000
1*
#2920000
1$
15
1+
0*
#2930000
b11110 "
b11110 6
b11110 8
1*
#2940000
0$
05
b11110 <
0+
0*
#2950000
1*
#2960000
1$
15
1+
0*
#2970000
b11111 "
b11111 6
b11111 8
1*
#2980000
0$
05
b11111 <
0+
0*
#2990000
1*
#3000000
1$
15
1+
0*
#3010000
b100000 "
b100000 6
b100000 8
1*
#3020000
0$
05
b100000 <
0+
0*
#3030000
1*
#3040000
1$
15
1+
0*
#3050000
b100001 "
b100001 6
b100001 8
1*
#3060000
0$
05
b100001 <
0+
0*
#3070000
1*
#3080000
1$
15
1+
0*
#3090000
b100010 "
b100010 6
b100010 8
1*
#3100000
0$
05
b100010 <
0+
0*
#3110000
1*
#3120000
1$
15
1+
0*
#3130000
b100011 "
b100011 6
b100011 8
1*
#3140000
0$
05
b100011 <
0+
0*
#3150000
1*
#3160000
1$
15
1+
0*
#3170000
b100100 "
b100100 6
b100100 8
1*
#3180000
0$
05
b100100 <
0+
0*
#3190000
1*
#3200000
1$
15
1+
0*
#3210000
b100101 "
b100101 6
b100101 8
1*
#3220000
0$
05
b100101 <
0+
0*
#3230000
1*
#3240000
1$
15
1+
0*
#3250000
b100110 "
b100110 6
b100110 8
1*
#3260000
0$
05
b100110 <
0+
0*
#3270000
1*
#3280000
1$
15
1+
0*
#3290000
b100111 "
b100111 6
b100111 8
1*
#3300000
0$
05
b100111 <
0+
0*
#3310000
1*
#3320000
1$
15
1+
0*
#3330000
b101000 "
b101000 6
b101000 8
1*
#3340000
0$
05
b101000 <
0+
0*
#3350000
1*
#3360000
1$
15
1+
0*
#3370000
b101001 "
b101001 6
b101001 8
1*
#3380000
0$
05
b101001 <
0+
0*
#3390000
1*
#3400000
1$
15
1+
0*
#3410000
b101010 "
b101010 6
b101010 8
1*
#3420000
0$
05
b101010 <
0+
0*
#3430000
1*
#3440000
1$
15
1+
0*
#3450000
b101011 "
b101011 6
b101011 8
1*
#3460000
0$
05
b101011 <
0+
0*
#3470000
1*
#3480000
1$
15
1+
0*
#3490000
b101100 "
b101100 6
b101100 8
1*
#3500000
0$
05
b101100 <
0+
0*
#3510000
1*
#3520000
1$
15
1+
0*
#3530000
b101101 "
b101101 6
b101101 8
1*
#3540000
0$
05
b101101 <
0+
0*
#3550000
1*
#3560000
1$
15
1+
0*
#3570000
b101110 "
b101110 6
b101110 8
1*
#3580000
0$
05
b101110 <
0+
0*
#3590000
1*
#3600000
1$
15
1+
0*
#3610000
b101111 "
b101111 6
b101111 8
1*
#3620000
0$
05
b101111 <
0+
0*
#3630000
1*
#3640000
1$
15
1+
0*
#3650000
b110000 "
b110000 6
b110000 8
1*
#3660000
0$
05
b110000 <
0+
0*
#3670000
1*
#3680000
1$
15
1+
0*
#3690000
b110001 "
b110001 6
b110001 8
1*
#3700000
0$
05
b110001 <
0+
0*
#3710000
1*
#3720000
1$
15
1+
0*
#3730000
b110010 "
b110010 6
b110010 8
1*
#3740000
0$
05
b110010 <
0+
0*
#3750000
1*
#3760000
1$
15
1+
0*
#3770000
b110011 "
b110011 6
b110011 8
1*
#3780000
0$
05
b110011 <
0+
0*
#3790000
1*
#3800000
1$
15
1+
0*
#3810000
b110100 "
b110100 6
b110100 8
1*
#3820000
0$
05
b110100 <
0+
0*
#3830000
1*
#3840000
1$
15
1+
0*
#3850000
b110101 "
b110101 6
b110101 8
1*
#3860000
0$
05
b110101 <
0+
0*
#3870000
1*
#3880000
1$
15
1+
0*
#3890000
b110110 "
b110110 6
b110110 8
1*
#3900000
0$
05
b110110 <
0+
0*
#3910000
1*
#3920000
1$
15
1+
0*
#3930000
b110111 "
b110111 6
b110111 8
1*
#3940000
0$
05
b110111 <
0+
0*
#3950000
1*
#3960000
1$
15
1+
0*
#3970000
b111000 "
b111000 6
b111000 8
1*
#3980000
0$
05
b111000 <
0+
0*
#3990000
1*
#4000000
1$
15
1+
0*
#4010000
b111001 "
b111001 6
b111001 8
1*
#4020000
0$
05
b111001 <
0+
0*
#4030000
1*
#4040000
1$
15
1+
0*
#4050000
b111010 "
b111010 6
b111010 8
1*
#4060000
0$
05
b111010 <
0+
0*
#4070000
1*
#4080000
1$
15
1+
0*
#4090000
b111011 "
b111011 6
b111011 8
1*
#4100000
0$
05
b111011 <
0+
0*
#4110000
1*
#4120000
1$
15
1+
0*
#4130000
b111100 "
b111100 6
b111100 8
1*
#4140000
0$
05
b111100 <
0+
0*
#4150000
1*
#4160000
1$
15
1+
0*
#4170000
b111101 "
b111101 6
b111101 8
1*
#4180000
0$
05
b111101 <
0+
0*
#4190000
1*
#4200000
1$
15
1+
0*
#4210000
b111110 "
b111110 6
b111110 8
1*
#4220000
0$
05
b111110 <
0+
0*
#4230000
1*
#4240000
1$
15
1+
0*
#4250000
b111111 "
b111111 6
b111111 8
1*
#4260000
0$
05
b111111 <
0+
0*
#4270000
1*
#4280000
1$
15
1+
0*
#4290000
b1000000 "
b1000000 6
b1000000 8
1*
#4300000
0$
05
b1000000 <
0+
0*
#4310000
1*
#4320000
1$
15
1+
0*
#4330000
b1000001 "
b1000001 6
b1000001 8
1*
#4340000
0$
05
b1000001 <
0+
0*
#4350000
1*
#4360000
1$
15
1+
0*
#4370000
b1000010 "
b1000010 6
b1000010 8
1*
#4380000
0$
05
b1000010 <
0+
0*
#4390000
1*
#4400000
1$
15
1+
0*
#4410000
b1000011 "
b1000011 6
b1000011 8
1*
#4420000
0$
05
b1000011 <
0+
0*
#4430000
1*
#4440000
1$
15
1+
0*
#4450000
b1000100 "
b1000100 6
b1000100 8
1*
#4460000
0$
05
b1000100 <
0+
0*
#4470000
1*
#4480000
1$
15
1+
0*
#4490000
b1000101 "
b1000101 6
b1000101 8
1*
#4500000
0$
05
b1000101 <
0+
0*
#4510000
1*
#4520000
1$
15
1+
0*
#4530000
b1000110 "
b1000110 6
b1000110 8
1*
#4540000
0$
05
b1000110 <
0+
0*
#4550000
1*
#4560000
1$
15
1+
0*
#4570000
b1000111 "
b1000111 6
b1000111 8
1*
#4580000
0$
05
b1000111 <
0+
0*
#4590000
1*
#4600000
1$
15
1+
0*
#4610000
b1001000 "
b1001000 6
b1001000 8
1*
#4620000
0$
05
b1001000 <
0+
0*
#4630000
1*
#4640000
1$
15
1+
0*
#4650000
b1001001 "
b1001001 6
b1001001 8
1*
#4660000
0$
05
b1001001 <
0+
0*
#4670000
1*
#4680000
1$
15
1+
0*
#4690000
b1001010 "
b1001010 6
b1001010 8
1*
#4700000
0$
05
b1001010 <
0+
0*
#4710000
1*
#4720000
1$
15
1+
0*
#4730000
b1001011 "
b1001011 6
b1001011 8
1*
#4740000
0$
05
b1001011 <
0+
0*
#4750000
1*
#4760000
1$
15
1+
0*
#4770000
b1001100 "
b1001100 6
b1001100 8
1*
#4780000
0$
05
b1001100 <
0+
0*
#4790000
1*
#4800000
1$
15
1+
0*
#4810000
b1001101 "
b1001101 6
b1001101 8
1*
#4820000
0$
05
b1001101 <
0+
0*
#4830000
1*
#4840000
1$
15
1+
0*
#4850000
b1001110 "
b1001110 6
b1001110 8
1*
#4860000
0$
05
b1001110 <
0+
0*
#4870000
1*
#4880000
1$
15
1+
0*
#4890000
b1001111 "
b1001111 6
b1001111 8
1*
#4900000
0$
05
b1001111 <
0+
0*
#4910000
1*
#4920000
1$
15
1+
0*
#4930000
b1010000 "
b1010000 6
b1010000 8
1*
#4940000
0$
05
b1010000 <
0+
0*
#4950000
1*
#4960000
1$
15
1+
0*
#4970000
b1010001 "
b1010001 6
b1010001 8
1*
#4980000
0$
05
b1010001 <
0+
0*
#4990000
1*
