rtl/can_acceptance.sv
//-----------------------------------------------------------------------------
// can_acceptance
// 4 filtros de aceitação (código + máscara), 11/29-bit. Política RESTRITIVA:
// só aceita se algum filtro HABILITADO casar (OR). Avaliação combinacional,
// registrada em check_strobe.
// mask bit = 1 -> don't care; mask bit = 0 -> deve casar.
//-----------------------------------------------------------------------------
module can_acceptance #(
    parameter int NUM_FILTERS = 4
)(
    input  logic             clk,
    input  logic             rst_n,

    // mensagem recebida (do FSM)
    input  logic [28:0]      id,
    input  logic             ide,

    // configuração (do reg_file)
    input  logic [29:0]      filt_code [NUM_FILTERS],   // {ide[29], id[28:0]}
    input  logic [29:0]      filt_mask [NUM_FILTERS],
    input  logic [NUM_FILTERS-1:0] filt_en,

    // strobe de avaliação
    input  logic             check_strobe,
    output logic             accept,
    output logic             reject
);

    logic accept_comb;

    always_comb begin
        accept_comb = 1'b0;
        for (int i = 0; i < NUM_FILTERS; i++) begin
            // match de ID (bits onde mask=0 devem casar)
            // match de IDE (se mask[29]=1 -> don't care)
            if (filt_en[i] &&
                ((id & ~filt_mask[i][28:0]) == (filt_code[i][28:0] & ~filt_mask[i][28:0])) &&
                (filt_mask[i][29] || (filt_code[i][29] == ide)))
                accept_comb = 1'b1;
        end
    end

    always_ff @(posedge clk or negedge rst_n) begin
        if (!rst_n) begin
            accept <= 1'b0;
            reject <= 1'b0;
        end else if (check_strobe) begin
            accept <= accept_comb;
            reject <= ~accept_comb;
        end
        // senão: mantém
    end

endmodule

uvm/testbench/tb_can_acceptance.sv
//-----------------------------------------------------------------------------
// tb_can_acceptance — Testbench SIMPLES (smoke test, self-checking, nao-UVM)
// do can_acceptance (4 filtros code+mask, política RESTRITIVA OR).
//
// Cobre:
//   - mask=0 (casa tudo) com filtro habilitado -> accept.
//   - filtro desabilitado (filt_en=0) -> reject.
//   - mask=1 (must match) com match -> accept, sem match -> reject.
//   - match de IDE quando mask[29]=0.
//   - comportamento sticky entre strobes.
//
// Rodar (Xcelium):
//   xrun -sv -access +rwc -timescale 1ns/1ps -f script/simlist_can.f \
//        uvm/testbench/tb_can_acceptance.sv
// Icarus:
//   iverilog -g2012 -t null -f script/simlist_can.f uvm/testbench/tb_can_acceptance.sv
//-----------------------------------------------------------------------------
`timescale 1ns/1ps

module tb_can_acceptance;

    localparam int N = 4;

    logic        clk = 1'b0;
    logic        rst_n;
    logic [28:0] id;
    logic        ide;
    logic [29:0] filt_code [N];
    logic [29:0] filt_mask [N];
    logic [N-1:0] filt_en;
    logic        check_strobe;
    logic        accept, reject;

    can_acceptance #(.NUM_FILTERS(N)) DUT (
        .clk(clk), .rst_n(rst_n),
        .id(id), .ide(ide),
        .filt_code(filt_code), .filt_mask(filt_mask), .filt_en(filt_en),
        .check_strobe(check_strobe),
        .accept(accept), .reject(reject)
    );

    always #10 clk = ~clk;

    integer errors;

    task chk(input bit cond, input string msg);
        begin
            if (!cond) begin errors = errors + 1; $display("[TB] FAIL: %s", msg); end
            else         $display("[TB] OK:   %s", msg);
        end
    endtask

    // Avalia com um strobe e checa accept/reject esperados
    task eval_check(input bit exp_accept, input string msg);
        begin
            @(negedge clk); check_strobe = 1'b1;
            @(negedge clk); check_strobe = 1'b0;
            @(posedge clk);
            chk(accept === exp_accept,             msg);
            chk(reject === ~exp_accept,            "reject= complemento de accept");
        end
    endtask

    initial begin
        $timeformat(-9, 3, " ns", 12);
        errors = 0;
        id = 29'b0; ide = 1'b0;
        for (int i = 0; i < N; i++) begin
            filt_code[i] = 30'b0;
            filt_mask[i] = 30'b0;
        end
        filt_en = 4'b0;
        check_strobe = 1'b0;

        $dumpfile("tb_can_acceptance.vcd");
        $dumpvars(0, tb_can_acceptance);

        rst_n = 1'b0;
        repeat (3) @(posedge clk);
        rst_n = 1'b1;
        @(posedge clk);

        $display("==========================================================");
        $display("[TB] tb_can_acceptance — smoke test");
        $display("==========================================================");

        // 1) Pós-reset: accept=0, reject=0 (sem strobe ainda)
        chk(accept === 1'b0, "accept=0 pos-reset");
        chk(reject === 1'b0, "reject=0 pos-reset");

        // 2) Sem filtro habilitado -> reject
        id = 29'h123; ide = 1'b0;
        eval_check(1'b0, "sem filtros habilitados -> reject");

        // 3) Filtro 0: mask=0 (casa tudo), habilitado -> accept
        filt_code[0] = 30'b0;
        filt_mask[0] = 30'h3FFFFFFF;   // todos don't care -> casa tudo
        filt_en      = 4'b0001;
        eval_check(1'b1, "filtro 0 mask all-dont-care -> accept");

        // 4) mask=0 (must match all), code != id -> reject
        filt_mask[0] = 30'b0;          // tudo deve casar
        filt_code[0] = {1'b0, 29'h00000123};
        id = 29'h00000124;             // ID diferente
        eval_check(1'b0, "mask=0 code=0x123 id=0x124 -> reject");

        // 5) mask=0, code == id -> accept
        id = 29'h00000123;
        eval_check(1'b1, "mask=0 code=0x123 id=0x123 -> accept");

        // 6) mask parcial: casa só baixos (id[10:0])
        //    mask[10:0]=1 (dont-care), code[28:11]=0, id[10:0] irrelevante
        filt_code[0] = {1'b0, 29'h0};
        filt_mask[0] = {1'b0, 29'h000007FF};   // dont-care nos 11 baixos
        id = 29'h000007FF;             // 11 baixos = 1, mas não importam
        eval_check(1'b1, "mask parcial (dont-care 11 baixos) -> accept");
        id = 29'h00800000;             // bit 23 seta -> casa alto? alto é code=0
        eval_check(1'b0, "mask parcial: alto difere -> reject");

        // 7) IDE mismatch quando mask[29]=0
        filt_code[0] = {1'b0, 29'h0};  // code[IDE]=0 (standard)
        filt_mask[0] = 30'h00000000;   // tudo must-match
        id = 29'h0; ide = 1'b0;        // standard -> casa
        eval_check(1'b1, "IDE code=0 / msg=0 -> accept");
        ide = 1'b1;                    // extended -> mismatch
        eval_check(1'b0, "IDE code=0 / msg=1 -> reject");

        // 8) IDE dont-care (mask[29]=1)
        filt_mask[0] = 30'h20000000;   // só IDE dont-care, resto must-match
        filt_code[0] = {1'b0, 29'h0};
        id = 29'h0; ide = 1'b0;
        eval_check(1'b1, "IDE dont-care, ID=0 standard -> accept");
        ide = 1'b1;
        eval_check(1'b1, "IDE dont-care, ID=0 extended -> accept");

        // 9) OR entre filtros: filtro 0 rejeita, filtro 1 aceita
        filt_mask[0] = 30'b0; filt_code[0] = {1'b0,29'h0};
        filt_mask[1] = 30'h3FFFFFFF; filt_code[1] = 30'h0;
        filt_en = 4'b0011;
        id = 29'hABC; ide = 1'b0;
        eval_check(1'b1, "OR: filtro 1 mask-all accept sobrepõe filtro 0");

        $display("----------------------------------------------------------");
        if (errors == 0) $display("[TB] ===== SMOKE TEST PASS =====");
        else             $display("[TB] ===== SMOKE TEST FAIL (%0d erros) =====", errors);
        $display("----------------------------------------------------------");
        $finish;
    end

    initial begin
        #1ms;
        $display("[TB] TIMEOUT global (1 ms). Abortando.");
        $finish;
    end

endmodule

vcd files/tb_can_acceptance.vcd
$date
	Tue Jul 07 22:07:19 2026
$end
$version
	Icarus Verilog
$end
$timescale
	1ps
$end
$scope module tb_can_acceptance $end
$var wire 1 ! reject $end
$var wire 1 " accept $end
$var parameter 32 # N $end
$var reg 1 $ check_strobe $end
$var reg 1 % clk $end
$var reg 4 & filt_en [3:0] $end
$var reg 29 ' id [28:0] $end
$var reg 1 ( ide $end
$var reg 1 ) rst_n $end
$var integer 32 * errors [31:0] $end
$scope module DUT $end
$var wire 1 $ check_strobe $end
$var wire 1 % clk $end
$var wire 4 + filt_en [3:0] $end
$var wire 29 , id [28:0] $end
$var wire 1 ( ide $end
$var wire 1 ) rst_n $end
$var parameter 32 - NUM_FILTERS $end
$var reg 1 " accept $end
$var reg 1 . accept_comb $end
$var reg 1 ! reject $end
$scope begin $ivl_for_loop0 $end
$var integer 32 / i [31:0] $end
$upscope $end
$upscope $end
$scope begin $ivl_for_loop1 $end
$var integer 32 0 i [31:0] $end
$upscope $end
$scope task chk $end
$var reg 1 1 cond $end
$upscope $end
$scope task eval_check $end
$var reg 1 2 exp_accept $end
$upscope $end
$upscope $end
$enddefinitions $end
$comment Show the parameter values. $end
$dumpall
b100 -
b100 #
$end
#0
$dumpvars
02
01
b100 0
b100 /
0.
b0 ,
b0 +
b0 *
0)
0(
b0 '
b0 &
0%
0$
0"
0!
$end
#10000
1%
#20000
0%
#30000
1%
#40000
0%
#50000
1)
1%
#60000
0%
#70000
b100 /
b100100011 '
b100100011 ,
11
1%
#80000
1$
0%
#90000
1!
1%
#100000
0$
0%
#110000
1.
b100 /
12
b1 &
b1 +
1%
#120000
1$
0%
#130000
0!
1"
1%
#140000
0$
0%
#150000
b100 /
0.
02
b100100100 '
b100100100 ,
1%
#160000
1$
0%
#170000
1!
0"
1%
#180000
0$
0%
#190000
1.
b100 /
12
b100100011 '
b100100011 ,
1%
#200000
1$
0%
#210000
0!
1"
1%
#220000
0$
0%
#230000
b100 /
1.
b11111111111 '
b11111111111 ,
1%
#240000
1$
0%
#250000
1%
#260000
0$
0%
#270000
b100 /
0.
02
b100000000000000000000000 '
b100000000000000000000000 ,
1%
#280000
1$
0%
#290000
1!
0"
1%
#300000
0$
0%
#310000
1.
b100 /
12
b0 '
b0 ,
1%
#320000
1$
0%
#330000
0!
1"
1%
#340000
0$
0%
#350000
b100 /
0.
02
1(
1%
#360000
1$
0%
#370000
1!
0"
1%
#380000
0$
0%
#390000
1.
b100 /
12
0(
1%
#400000
1$
0%
#410000
0!
1"
1%
#420000
0$
0%
#430000
b100 /
1.
1(
1%
#440000
1$
0%
#450000
1%
#460000
0$
0%
#470000
b100 /
1.
0(
b101010111100 '
b101010111100 ,
b11 &
b11 +
1%
#480000
1$
0%
#490000
1%
#500000
0$
0%
