rtl/can_bsp.sv
//-----------------------------------------------------------------------------
// can_bsp  (Bit Stream Processor)
// Serializa (TX) e desserializa (RX) o fluxo de bits no barramento CAN,
// aplicando/removendo bit-stuffing (NRZ) e drive/amostra da linha física.
// Único módulo que drive can_tx. Alimenta o CRC com bits destuffed/pre-stuff.
//
// Handshake de stuffing: o FSM avança por BIT DE PROTOCOLO, não por bit de
// barramento. Em TX, tx_bit_done pulsa quando um bit de protocolo foi
// consumido (1 a cada bit-time, exceto quando um stuff-bit é inserido). Em RX,
// rx_valid pulsa a cada bit destuffed (stuff-bits são descartados e não geram
// rx_valid). Assim o FSM desloca seus contadores/registradores nessas strobes.
// Contadores de stuffing correm contínuos; stuff_en só habilita descarte/erro.
//-----------------------------------------------------------------------------
module can_bsp (
    input  logic        clk,
    input  logic        rst_n,

    // cadenciamento (do BTU)
    input  logic        bit_tick,     // início do bit (TQ=0)
    input  logic        sample_tick,  // ponto de amostragem

    // TX (do FSM)
    input  logic        tx_bit,       // bit de protocolo a transmitir (pré-stuff)
    input  logic        tx_valid,     // tx_bit é válido neste bit-time
    input  logic        stuff_en,     // 1 = aplicar stuffing na região atual

    // bus físico
    input  logic        can_rx,       // linha recebida
    output logic        can_tx,       // linha transmitida
    output logic        can_tx_oe,    // output-enable (1 quando transmitindo)

    // RX (para FSM)
    output logic        rx_bit,       // bit recebido destuffed
    output logic        rx_valid,     // 1 pulso por bit destuffed (alinhado a sample_tick)

    // consumo TX (para FSM) — strobe por bit de protocolo consumido
    output logic        tx_bit_done,

    // CRC (alimentação — bits destuffed/pre-stuff)
    output logic        bit_to_crc,
    output logic        crc_bit_valid,

    // status
    output logic        stuff_error,  // 6 bits iguais em região stuffed
    output logic        bsp_busy
);

    localparam logic CAN_RECESSIVE = 1'b1;
    localparam logic CAN_DOMINANT  = 1'b0;

    // ---- estado de stuffing TX ----
    logic [3:0] tx_consec_r;   // run de bits idênticos na saída (0..15, sat)
    logic       tx_last_r;     // último bit de saída
    logic       tx_out_r;      // bit atualmente drivado (segurado p/ o bit-time)
    logic       oe_r;          // output enable registrado
    logic       tx_bit_done_r;

    // ---- estado de stuffing RX ----
    logic [3:0] rx_consec_r;   // run de bits idênticos recebidos (0..15, sat)
    logic       rx_last_r;
    logic       rx_bit_r;
    logic       rx_valid_r;
    logic       stuff_error_r;

    always_ff @(posedge clk or negedge rst_n) begin
        if (!rst_n) begin
            tx_consec_r   <= 4'd0;
            tx_last_r     <= CAN_RECESSIVE;
            tx_out_r      <= CAN_RECESSIVE;
            oe_r          <= 1'b0;
            tx_bit_done_r <= 1'b0;
            rx_consec_r   <= 4'd0;
            rx_last_r     <= CAN_RECESSIVE;
            rx_bit_r      <= CAN_RECESSIVE;
            rx_valid_r    <= 1'b0;
            stuff_error_r <= 1'b0;
        end else begin
            // defaults (pulsos de 1 ciclo)
            tx_bit_done_r <= 1'b0;
            rx_valid_r    <= 1'b0;
            stuff_error_r <= 1'b0;

            // ============ TX (decide em bit_tick; segura por todo o bit-time) ===
            if (bit_tick) begin
                if (!tx_valid) begin
                    // ocioso: libera o bus e zera o contador de stuffing
                    tx_consec_r <= 4'd0;
                    tx_last_r   <= CAN_RECESSIVE;
                    oe_r        <= 1'b0;
                    tx_out_r    <= CAN_RECESSIVE;
                end else begin
                    oe_r <= 1'b1;
                    if (stuff_en && (tx_consec_r == 4'd5)) begin
                        // insere stuff-bit (oposto) sem consumir tx_bit
                        tx_out_r    <= ~tx_last_r;
                        tx_consec_r <= 4'd1;
                        tx_last_r   <= ~tx_last_r;
                    end else begin
                        // consome bit de protocolo
                        tx_out_r      <= tx_bit;
                        tx_bit_done_r <= 1'b1;
                        if (tx_bit != tx_last_r) begin
                            tx_consec_r <= 4'd1;
                            tx_last_r   <= tx_bit;
                        end else if (tx_consec_r < 4'd15) begin
                            tx_consec_r <= tx_consec_r + 4'd1;
                        end
                    end
                end
            end

            // ============ RX (destuffing em sample_tick) ========================
            if (sample_tick) begin
                if (stuff_en && (rx_consec_r == 4'd5)) begin
                    // bit esperado como stuff-bit
                    if (can_rx == rx_last_r) begin
                        // 6 idênticos consecutivos -> stuff error
                        stuff_error_r <= 1'b1;
                        rx_bit_r      <= can_rx;
                        rx_valid_r    <= 1'b1;
                        rx_consec_r   <= 4'd1;
                        rx_last_r     <= can_rx;
                    end else begin
                        // stuff-bit válido (oposto): descarta, não emite rx_valid
                        rx_consec_r <= 4'd1;
                        rx_last_r   <= can_rx;
                    end
                end else begin
                    // bit normal (ou região não-stuffed): repassa
                    rx_bit_r   <= can_rx;
                    rx_valid_r <= 1'b1;
                    if (can_rx != rx_last_r) begin
                        rx_consec_r <= 4'd1;
                        rx_last_r   <= can_rx;
                    end else if (rx_consec_r < 4'd15) begin
                        rx_consec_r <= rx_consec_r + 4'd1;
                    end
                end
            end
        end
    end

    // ---- saídas ----
    assign can_tx       = oe_r ? tx_out_r : CAN_RECESSIVE;
    assign can_tx_oe    = oe_r;
    assign rx_bit       = rx_bit_r;
    assign rx_valid     = rx_valid_r;
    assign tx_bit_done  = tx_bit_done_r;
    assign stuff_error  = stuff_error_r;
    assign bsp_busy     = oe_r;

    // CRC: em TX alimenta o bit de protocolo (pré-stuff); em RX o bit destuffed.
    // crc_bit_valid é a strobe de bit-de-protocolo (o FSM gera crc_shift no
    // janela SOF..DATA a partir dela).
    assign bit_to_crc   = tx_valid ? tx_bit  : rx_bit_r;
    assign crc_bit_valid = tx_valid ? tx_bit_done_r : rx_valid_r;

endmodule

uvm/testbench/tb_can_bsp.sv
//-----------------------------------------------------------------------------
// tb_can_bsp — Testbench SIMPLES (smoke test, self-checking, nao-UVM) do
// can_bsp (Bit Stream Processor).
//
// O TB atua como BTU+FSM: gera bit_tick (início do bit) e sample_tick (ponto
// de amostragem), e fornece tx_bit/tx_valid/stuff_en. As capturas de can_tx
// e strobes são feitas no NEGEDGE após o posedge que processa o pulso, para
// evitar race com o always_ff (região NBA).
//
// Cobre:
//   - TX sem stuffing (bits alternados): can_tx segue tx_bit; 1 strobe
//     tx_bit_done por bit consumido.
//   - TX COM stuffing: 5 bits dominantes consecutivos -> no 6º bit-time o BSP
//     insere stuff-bit recessivo; tx_bit_done NÃO pulsa nesse bit-time.
//   - RX destuffing: stuff-bit válido descartado (sem rx_valid); 6 idênticos
//     em região stuffed -> stuff_error.
//   - OE libera quando tx_valid=0.
//
// Rodar (Xcelium):
//   xrun -sv -access +rwc -timescale 1ns/1ps -f script/simlist_can.f \
//        uvm/testbench/tb_can_bsp.sv
// Icarus:
//   iverilog -g2012 -t null -I rtl rtl/can_bsp.sv uvm/testbench/tb_can_bsp.sv
//-----------------------------------------------------------------------------
`timescale 1ns/1ps

module tb_can_bsp;

    logic clk = 1'b0;
    logic rst_n;
    logic bit_tick, sample_tick;
    logic tx_bit, tx_valid, stuff_en;
    logic can_rx;
    logic can_tx, can_tx_oe;
    logic rx_bit, rx_valid, tx_bit_done;
    logic bit_to_crc, crc_bit_valid;
    logic stuff_error, bsp_busy;

    can_bsp DUT (
        .clk(clk), .rst_n(rst_n),
        .bit_tick(bit_tick), .sample_tick(sample_tick),
        .tx_bit(tx_bit), .tx_valid(tx_valid), .stuff_en(stuff_en),
        .can_rx(can_rx), .can_tx(can_tx), .can_tx_oe(can_tx_oe),
        .rx_bit(rx_bit), .rx_valid(rx_valid), .tx_bit_done(tx_bit_done),
        .bit_to_crc(bit_to_crc), .crc_bit_valid(crc_bit_valid),
        .stuff_error(stuff_error), .bsp_busy(bsp_busy)
    );

    always #10 clk = ~clk;

    integer errors;

    task chk(input bit cond, input string msg);
        begin
            if (!cond) begin errors = errors + 1; $display("[TB] FAIL: %s", msg); end
            else         $display("[TB] OK:   %s", msg);
        end
    endtask

    //---- TX bit-time: transmite 1 bit de protocolo (tx_valid=1) ----
    // Estrutura (cada '-' é meio ciclo):
    //   neg(bit_tick=1) | pos[always_ff processa] | neg(bit_tick=0, captura)
    //   depois alguns ciclos + sample_tick opcional
    task tx_bit_time(input logic b, input logic stuff_on,
                     output logic seen_tx, output logic seen_done);
        begin
            tx_bit = b; tx_valid = 1'b1; stuff_en = stuff_on;
            @(negedge clk); bit_tick = 1'b1;
            @(posedge clk);              // always_ff vê bit_tick=1
            @(negedge clk); bit_tick = 1'b0;
            // NBA já resolveu: oe_r/tx_out_r/tx_bit_done_r estão atualizados
            seen_tx   = can_tx;
            seen_done = tx_bit_done;
            // completa o bit-time (sample_tick no meio p/ completar TQs)
            repeat (2) @(posedge clk);
            @(negedge clk); sample_tick = 1'b1;
            @(posedge clk);
            @(negedge clk); sample_tick = 1'b0;
            repeat (2) @(posedge clk);
        end
    endtask

    //---- RX bit-time: o TB provê can_rx; o BSP amostra em sample_tick ----
    task rx_bit_time(input logic buslvl, input logic stuff_on,
                     output logic seen_rxbit, output logic seen_rxvalid,
                     output logic seen_stufferr);
        begin
            tx_valid = 1'b0; stuff_en = stuff_on; can_rx = buslvl;
            @(negedge clk); bit_tick = 1'b1;
            @(posedge clk);
            @(negedge clk); bit_tick = 1'b0;
            repeat (2) @(posedge clk);
            @(negedge clk); sample_tick = 1'b1;
            @(posedge clk);              // always_ff vê sample_tick=1
            @(negedge clk); sample_tick = 1'b0;
            // NBA resolveu: rx_bit_r/rx_valid_r/stuff_error_r atualizados
            seen_rxbit    = rx_bit;
            seen_rxvalid  = rx_valid;
            seen_stufferr = stuff_error;
            repeat (2) @(posedge clk);
        end
    endtask

    logic seen_tx, seen_done, seen_rxb, seen_rxv, seen_se;

    initial begin
        $timeformat(-9, 3, " ns", 12);
        errors = 0;
        bit_tick = 1'b0; sample_tick = 1'b0;
        tx_bit = 1'b1; tx_valid = 1'b0; stuff_en = 1'b0;
        can_rx = 1'b1;

        $dumpfile("tb_can_bsp.vcd");
        $dumpvars(0, tb_can_bsp);

        rst_n = 1'b0;
        repeat (3) @(posedge clk);
        rst_n = 1'b1;
        @(posedge clk);

        $display("==========================================================");
        $display("[TB] tb_can_bsp — smoke test");
        $display("==========================================================");

        // 1) Pós-reset: ocioso, bus recessivo, OE=0
        chk(can_tx === 1'b1,    "can_tx recessivo pos-reset");
        chk(can_tx_oe === 1'b0, "can_tx_oe=0 pos-reset");
        chk(bsp_busy === 1'b0,  "bsp_busy=0 pos-reset");

        // 2) TX sem stuffing: seq 0,1,0,1 (alternada) -> não insere stuff-bit,
        //    1 tx_bit_done por bit. stuff_en=0 para garantir.
        $display("[TB] -- TX sem stuffing (alternado) --");
        for (int i = 0; i < 4; i++) begin
            logic b = i[0];   // 0,1,0,1
            tx_bit_time(b, 1'b0, seen_tx, seen_done);
            chk(seen_done === 1'b1, $sformatf("TX bit %0d: tx_bit_done pulsa", i));
            chk(seen_tx   === b,    $sformatf("TX bit %0d: can_tx == %b", i, b));
        end

        // 3) TX COM stuffing: 5 dominantes consecutivos com stuff_en=1
        //    -> no 6º bit-time, é esperado um stuff-bit (recessivo, oposto)
        //    inserido; nesse bit-time tx_bit_done NÃO pulsa.
        $display("[TB] -- TX com stuffing (5x dominante) --");
        // Reinicia a corrida com 1 recessivo para garantir contagem limpa:
        tx_bit_time(1'b1, 1'b0, seen_tx, seen_done);  // 1 recessivo (sem stuff)
        chk(seen_done === 1'b1, "1 recessivo inicial consumido");
        // Agora 5 dominantes com stuff_en=1
        for (int i = 0; i < 5; i++) begin
            tx_bit_time(1'b0, 1'b1, seen_tx, seen_done);
            chk(seen_tx   === 1'b0, $sformatf("TX dom %0d: can_tx dominante", i));
            chk(seen_done === 1'b1, $sformatf("TX dom %0d: tx_bit_done (bit consumido)", i));
        end
        // 6º bit-time: stuff-bit deve ser inserido (recessivo), sem consumir.
        // Próximo tx_bit continua dominante -> após stuff, drive dominante
        // novamente no bit seguinte.
        tx_bit = 1'b0; tx_valid = 1'b1; stuff_en = 1'b1;
        @(negedge clk); bit_tick = 1'b1;
        @(posedge clk);              // always_ff decide: consec==5, insere stuff
        @(negedge clk); bit_tick = 1'b0;
        chk(can_tx === 1'b1,     "TX: 6o bit-time insere stuff-bit recessivo");
        chk(tx_bit_done === 1'b0, "TX: stuff-bit NAO consome (tx_bit_done=0)");
        repeat (4) @(posedge clk);
        tx_valid = 1'b0;

        // 4) RX destuffing: stuff-bit válido é descartado (sem rx_valid).
        $display("[TB] -- RX destuffing --");
        // limpa estado: alguns recessivos (não conta para stuff em região stuff)
        for (int i = 0; i < 3; i++) rx_bit_time(1'b1, 1'b1, seen_rxb, seen_rxv, seen_se);
        // Agora 5 dominantes em região stuff -> no 6º bit-time entra stuff-bit
        for (int i = 0; i < 5; i++) begin
            rx_bit_time(1'b0, 1'b1, seen_rxb, seen_rxv, seen_se);
            chk(seen_rxv === 1'b1, $sformatf("RX dom %0d: rx_valid (bit normal)", i));
            chk(seen_rxb === 1'b0, $sformatf("RX dom %0d: rx_bit dominante", i));
        end
        // 6º bit: stuff-bit (recessivo) esperado -> descartado, sem rx_valid
        rx_bit_time(1'b1, 1'b1, seen_rxb, seen_rxv, seen_se);
        chk(seen_rxv === 1'b0, "RX stuff-bit recessivo: descartado (rx_valid=0)");
        chk(seen_se === 1'b0,  "RX stuff-bit valido: sem stuff_error");

        // 5) RX stuff error: 6 idênticos consecutivos em região stuffed
        $display("[TB] -- RX stuff error (6x dominante) --");
        for (int i = 0; i < 3; i++) rx_bit_time(1'b1, 1'b1, seen_rxb, seen_rxv, seen_se);
        // 5 dominantes normais + 1 extra = 6º -> stuff_error
        for (int i = 0; i < 5; i++)
            rx_bit_time(1'b0, 1'b1, seen_rxb, seen_rxv, seen_se);
        rx_bit_time(1'b0, 1'b1, seen_rxb, seen_rxv, seen_se);
        chk(seen_se === 1'b1, "RX 6 idênticos -> stuff_error");
        chk(seen_rxv === 1'b1, "RX stuff error ainda emite rx_valid");

        // 6) OE libera quando tx_valid=0
        tx_valid = 1'b0;
        @(negedge clk); bit_tick = 1'b1;
        @(posedge clk);
        @(negedge clk); bit_tick = 1'b0;
        chk(can_tx_oe === 1'b0, "tx_valid=0 em bit_tick -> OE=0 (libera bus)");
        repeat (4) @(posedge clk);

        $display("----------------------------------------------------------");
        if (errors == 0) $display("[TB] ===== SMOKE TEST PASS =====");
        else             $display("[TB] ===== SMOKE TEST FAIL (%0d erros) =====", errors);
        $display("----------------------------------------------------------");
        $finish;
    end

    initial begin
        #5ms;
        $display("[TB] TIMEOUT global (5 ms). Abortando.");
        $finish;
    end

endmodule

vcd files/tb_can_bsp.vcd
$date
	Tue Jul 07 22:07:19 2026
$end
$version
	Icarus Verilog
$end
$timescale
	1ps
$end
$scope module tb_can_bsp $end
$var wire 1 ! tx_bit_done $end
$var wire 1 " stuff_error $end
$var wire 1 # rx_valid $end
$var wire 1 $ rx_bit $end
$var wire 1 % crc_bit_valid $end
$var wire 1 & can_tx_oe $end
$var wire 1 ' can_tx $end
$var wire 1 ( bsp_busy $end
$var wire 1 ) bit_to_crc $end
$var reg 1 * bit_tick $end
$var reg 1 + can_rx $end
$var reg 1 , clk $end
$var reg 1 - rst_n $end
$var reg 1 . sample_tick $end
$var reg 1 / seen_done $end
$var reg 1 0 seen_rxb $end
$var reg 1 1 seen_rxv $end
$var reg 1 2 seen_se $end
$var reg 1 3 seen_tx $end
$var reg 1 4 stuff_en $end
$var reg 1 5 tx_bit $end
$var reg 1 6 tx_valid $end
$var integer 32 7 errors [31:0] $end
$scope module DUT $end
$var wire 1 * bit_tick $end
$var wire 1 ( bsp_busy $end
$var wire 1 + can_rx $end
$var wire 1 & can_tx_oe $end
$var wire 1 , clk $end
$var wire 1 - rst_n $end
$var wire 1 $ rx_bit $end
$var wire 1 # rx_valid $end
$var wire 1 . sample_tick $end
$var wire 1 4 stuff_en $end
$var wire 1 " stuff_error $end
$var wire 1 5 tx_bit $end
$var wire 1 ! tx_bit_done $end
$var wire 1 6 tx_valid $end
$var wire 1 % crc_bit_valid $end
$var wire 1 ' can_tx $end
$var wire 1 ) bit_to_crc $end
$var parameter 1 8 CAN_DOMINANT $end
$var parameter 1 9 CAN_RECESSIVE $end
$var reg 1 : oe_r $end
$var reg 1 ; rx_bit_r $end
$var reg 4 < rx_consec_r [3:0] $end
$var reg 1 = rx_last_r $end
$var reg 1 > rx_valid_r $end
$var reg 1 ? stuff_error_r $end
$var reg 1 @ tx_bit_done_r $end
$var reg 4 A tx_consec_r [3:0] $end
$var reg 1 B tx_last_r $end
$var reg 1 C tx_out_r $end
$upscope $end
$scope begin $ivl_for_loop0 $end
$var integer 32 D i [31:0] $end
$scope begin $unm_blk_23 $end
$var reg 1 E b $end
$upscope $end
$upscope $end
$scope begin $ivl_for_loop1 $end
$var integer 32 F i [31:0] $end
$upscope $end
$scope begin $ivl_for_loop2 $end
$var integer 32 G i [31:0] $end
$upscope $end
$scope begin $ivl_for_loop3 $end
$var integer 32 H i [31:0] $end
$upscope $end
$scope begin $ivl_for_loop4 $end
$var integer 32 I i [31:0] $end
$upscope $end
$scope begin $ivl_for_loop5 $end
$var integer 32 J i [31:0] $end
$upscope $end
$scope task chk $end
$var reg 1 K cond $end
$upscope $end
$scope task rx_bit_time $end
$var reg 1 L buslvl $end
$var reg 1 M seen_rxbit $end
$var reg 1 N seen_rxvalid $end
$var reg 1 O seen_stufferr $end
$var reg 1 P stuff_on $end
$upscope $end
$scope task tx_bit_time $end
$var reg 1 Q b $end
$var reg 1 R seen_done $end
$var reg 1 S seen_tx $end
$var reg 1 T stuff_on $end
$upscope $end
$upscope $end
$enddefinitions $end
$comment Show the parameter values. $end
$dumpall
19
08
$end
#0
$dumpvars
xT
xS
xR
xQ
xP
xO
xN
xM
xL
0K
b0 J
b0 I
b0 H
b0 G
b0 F
0E
b0 D
1C
1B
b0 A
0@
0?
0>
1=
b0 <
1;
0:
b0 7
06
15
04
x3
x2
x1
x0
x/
0.
0-
0,
1+
0*
1)
0(
1'
0&
0%
1$
0#
0"
0!
$end
#10000
1,
#20000
0,
#30000
1,
#40000
0,
#50000
1-
1,
#60000
0,
#70000
0)
16
05
0T
0Q
1K
1,
#80000
1*
0,
#90000
1%
0'
0B
b1 A
1!
1@
0C
1(
1&
1:
1,
#100000
1R
0S
0*
0,
#110000
0%
0!
0@
1,
#120000
0,
#130000
1,
#140000
1.
0,
#150000
b1 <
1#
1>
1,
#160000
0.
0,
#170000
0#
0>
1,
#180000
0,
#190000
b1 D
1/
03
1,
#200000
1*
0,
#210000
1%
b10 A
1!
1@
1,
#220000
0*
0,
#230000
0%
0!
0@
1,
#240000
0,
#250000
1,
#260000
1.
0,
#270000
b10 <
1#
1>
1,
#280000
0.
0,
#290000
0#
0>
1,
#300000
0,
#310000
b10 D
1,
#320000
1*
0,
#330000
1%
b11 A
1!
1@
1,
#340000
0*
0,
#350000
0%
0!
0@
1,
#360000
0,
#370000
1,
#380000
1.
0,
#390000
b11 <
1#
1>
1,
#400000
0.
0,
#410000
0#
0>
1,
#420000
0,
#430000
b11 D
1,
#440000
1*
0,
#450000
1%
b100 A
1!
1@
1,
#460000
0*
0,
#470000
0%
0!
0@
1,
#480000
0,
#490000
1,
#500000
1.
0,
#510000
b100 <
1#
1>
1,
#520000
0.
0,
#530000
0#
0>
1,
#540000
0,
#550000
1)
15
1Q
b100 D
1,
#560000
1*
0,
#570000
1%
1'
1B
b1 A
1!
1@
1C
1,
#580000
1S
0*
0,
#590000
0%
0!
0@
1,
#600000
0,
#610000
1,
#620000
1.
0,
#630000
b101 <
1#
1>
1,
#640000
0.
0,
#650000
0#
0>
1,
#660000
0,
#670000
0)
14
05
1T
0Q
13
1,
#680000
1*
0,
#690000
1%
0'
0B
1!
1@
0C
1,
#700000
0S
0*
0,
#710000
0%
0!
0@
1,
#720000
0,
#730000
1,
#740000
1.
0,
#750000
b1 <
1#
1>
1"
1?
1,
#760000
0.
0,
#770000
0"
0?
0#
0>
1,
#780000
0,
#790000
b1 F
03
1,
#800000
1*
0,
#810000
1%
b10 A
1!
1@
1,
#820000
0*
0,
#830000
0%
0!
0@
1,
#840000
0,
#850000
1,
#860000
1.
0,
#870000
b10 <
1#
1>
1,
#880000
0.
0,
#890000
0#
0>
1,
#900000
0,
#910000
b10 F
1,
#920000
1*
0,
#930000
1%
b11 A
1!
1@
1,
#940000
0*
0,
#950000
0%
0!
0@
1,
#960000
0,
#970000
1,
#980000
1.
0,
#990000
b11 <
1#
1>
1,
#1000000
0.
0,
#1010000
0#
0>
1,
#1020000
0,
#1030000
b11 F
1,
#1040000
1*
0,
#1050000
1%
b100 A
1!
1@
1,
#1060000
0*
0,
#1070000
0%
0!
0@
1,
#1080000
0,
#1090000
1,
#1100000
1.
0,
#1110000
b100 <
1#
1>
1,
#1120000
0.
0,
#1130000
0#
0>
1,
#1140000
0,
#1150000
b100 F
1,
#1160000
1*
0,
#1170000
1%
b101 A
1!
1@
1,
#1180000
0*
0,
#1190000
0%
0!
0@
1,
#1200000
0,
#1210000
1,
#1220000
1.
0,
#1230000
b101 <
1#
1>
1,
#1240000
0.
0,
#1250000
0#
0>
1,
#1260000
0,
#1270000
b101 F
1,
#1280000
1*
0,
#1290000
1'
1B
b1 A
1C
1,
#1300000
0*
0,
#1310000
1,
#1320000
0,
#1330000
1,
#1340000
0,
#1350000
1,
#1360000
0,
#1370000
1)
1P
1L
06
1,
#1380000
1*
0,
#1390000
0(
0&
0:
b0 A
1,
#1400000
0*
0,
#1410000
1,
#1420000
0,
#1430000
1,
#1440000
1.
0,
#1450000
1%
b1 <
1#
1>
1"
1?
1,
#1460000
1O
1N
1M
0.
0,
#1470000
0%
0"
0?
0#
0>
1,
#1480000
0,
#1490000
b1 G
12
11
10
1,
#1500000
1*
0,
#1510000
1,
#1520000
0*
0,
#1530000
1,
#1540000
0,
#1550000
1,
#1560000
1.
0,
#1570000
1%
b10 <
1#
1>
1,
#1580000
0O
0.
0,
#1590000
0%
0#
0>
1,
#1600000
0,
#1610000
b10 G
02
1,
#1620000
1*
0,
#1630000
1,
#1640000
0*
0,
#1650000
1,
#1660000
0,
#1670000
1,
#1680000
1.
0,
#1690000
1%
b11 <
1#
1>
1,
#1700000
0.
0,
#1710000
0%
0#
0>
1,
#1720000
0,
#1730000
0+
0L
b11 G
1,
#1740000
1*
0,
#1750000
1,
#1760000
0*
0,
#1770000
1,
#1780000
0,
#1790000
1,
#1800000
1.
0,
#1810000
1%
0)
0=
b1 <
1#
1>
0$
0;
1,
#1820000
0M
0.
0,
#1830000
0%
0#
0>
1,
#1840000
0,
#1850000
b1 H
00
1,
#1860000
1*
0,
#1870000
1,
#1880000
0*
0,
#1890000
1,
#1900000
0,
#1910000
1,
#1920000
1.
0,
#1930000
1%
b10 <
1#
1>
1,
#1940000
0.
0,
#1950000
0%
0#
0>
1,
#1960000
0,
#1970000
b10 H
1,
#1980000
1*
0,
#1990000
1,
#2000000
0*
0,
#2010000
1,
#2020000
0,
#2030000
1,
#2040000
1.
0,
#2050000
1%
b11 <
1#
1>
1,
#2060000
0.
0,
#2070000
0%
0#
0>
1,
#2080000
0,
#2090000
b11 H
1,
#2100000
1*
0,
#2110000
1,
#2120000
0*
0,
#2130000
1,
#2140000
0,
#2150000
1,
#2160000
1.
0,
#2170000
1%
b100 <
1#
1>
1,
#2180000
0.
0,
#2190000
0%
0#
0>
1,
#2200000
0,
#2210000
b100 H
1,
#2220000
1*
0,
#2230000
1,
#2240000
0*
0,
#2250000
1,
#2260000
0,
#2270000
1,
#2280000
1.
0,
#2290000
1%
b101 <
1#
1>
1,
#2300000
0.
0,
#2310000
0%
0#
0>
1,
#2320000
0,
#2330000
1+
1L
b101 H
1,
#2340000
1*
0,
#2350000
1,
#2360000
0*
0,
#2370000
1,
#2380000
0,
#2390000
1,
#2400000
1.
0,
#2410000
1=
b1 <
1,
#2420000
0N
0.
0,
#2430000
1,
#2440000
0,
#2450000
01
1,
#2460000
1*
0,
#2470000
1,
#2480000
0*
0,
#2490000
1,
#2500000
0,
#2510000
1,
#2520000
1.
0,
#2530000
1%
1)
b10 <
1#
1>
1$
1;
1,
#2540000
1N
1M
0.
0,
#2550000
0%
0#
0>
1,
#2560000
0,
#2570000
b1 I
11
10
1,
#2580000
1*
0,
#2590000
1,
#2600000
0*
0,
#2610000
1,
#2620000
0,
#2630000
1,
#2640000
1.
0,
#2650000
1%
b11 <
1#
1>
1,
#2660000
0.
0,
#2670000
0%
0#
0>
1,
#2680000
0,
#2690000
b10 I
1,
#2700000
1*
0,
#2710000
1,
#2720000
0*
0,
#2730000
1,
#2740000
0,
#2750000
1,
#2760000
1.
0,
#2770000
1%
b100 <
1#
1>
1,
#2780000
0.
0,
#2790000
0%
0#
0>
1,
#2800000
0,
#2810000
0+
0L
b11 I
1,
#2820000
1*
0,
#2830000
1,
#2840000
0*
0,
#2850000
1,
#2860000
0,
#2870000
1,
#2880000
1.
0,
#2890000
1%
0)
0=
b1 <
1#
1>
0$
0;
1,
#2900000
0M
0.
0,
#2910000
0%
0#
0>
1,
#2920000
0,
#2930000
b1 J
00
1,
#2940000
1*
0,
#2950000
1,
#2960000
0*
0,
#2970000
1,
#2980000
0,
#2990000
1,
#3000000
1.
0,
#3010000
1%
b10 <
1#
1>
1,
#3020000
0.
0,
#3030000
0%
0#
0>
1,
#3040000
0,
#3050000
b10 J
1,
#3060000
1*
0,
#3070000
1,
#3080000
0*
0,
#3090000
1,
#3100000
0,
#3110000
1,
#3120000
1.
0,
#3130000
1%
b11 <
1#
1>
1,
#3140000
0.
0,
#3150000
0%
0#
0>
1,
#3160000
0,
#3170000
b11 J
1,
#3180000
1*
0,
#3190000
1,
#3200000
0*
0,
#3210000
1,
#3220000
0,
#3230000
1,
#3240000
1.
0,
#3250000
1%
b100 <
1#
1>
1,
#3260000
0.
0,
#3270000
0%
0#
0>
1,
#3280000
0,
#3290000
b100 J
1,
#3300000
1*
0,
#3310000
1,
#3320000
0*
0,
#3330000
1,
#3340000
0,
#3350000
1,
#3360000
1.
0,
#3370000
1%
b101 <
1#
1>
1,
#3380000
0.
0,
#3390000
0%
0#
0>
1,
#3400000
0,
#3410000
b101 J
1,
#3420000
1*
0,
#3430000
1,
#3440000
0*
0,
#3450000
1,
#3460000
0,
#3470000
1,
#3480000
1.
0,
#3490000
1%
b1 <
1#
1>
1"
1?
1,
#3500000
1O
0.
0,
#3510000
0%
0"
0?
0#
0>
1,
#3520000
0,
#3530000
12
1,
#3540000
1*
0,
#3550000
1,
#3560000
0*
0,
